Workbook

Sheet DASHBOARD
A1: Cohen CUARC Graph Dashboard
A3: Key Metrics
A4: Total Edges | B4: =COUNTA(EDGES!A:A)-1
A5: Quote-Compliant Edges (YES) | B5: =COUNTIF(EDGES!N:N,"YES")
A6: Quote-Compliant % | B6: =IF(B4=0,0,B5/B4)
A8: Anchor Upgrades Needed | B8: =COUNTA(ANCHOR_UPGRADE!A:A)-1
A9: Record Items requiring ingestion | B9: =COUNTIF(RECORD_ITEMS!S:S,"YES")
A10: Open Contradictions | B10: =COUNTIF(CONTRADICTIONS!N:N,"OPEN")
A12: Issue Readiness
A13: Issue | B13: Status | C13: Support edges (Quote YES) | D13: Anchor upgrades linked | E13: Open contradictions
A14: I-DAMAGES | B14: draft-safe | C14: =COUNTIFS(EDGES!C:C,"I-DAMAGES",EDGES!N:N,"YES") | D14: =COUNTIF(ANCHOR_UPGRADE!E:E,"I-DAMAGES") | E14: =COUNTIFS(CONTRADICTIONS!B:B,"I-DAMAGES",CONTRADICTIONS!N:N,"OPEN")
A15: I-SPOLIATION | B15: draft-safe | C15: =COUNTIFS(EDGES!C:C,"I-SPOLIATION",EDGES!N:N,"YES") | D15: =COUNTIF(ANCHOR_UPGRADE!E:E,"I-SPOLIATION") | E15: =COUNTIFS(CONTRADICTIONS!B:B,"I-SPOLIATION",CONTRADICTIONS!N:N,"OPEN")
A16: I-SECDEP | B16: needs_record | C16: =COUNTIFS(EDGES!C:C,"I-SECDEP",EDGES!N:N,"YES") | D16: =COUNTIF(ANCHOR_UPGRADE!E:E,"I-SECDEP") | E16: =COUNTIFS(CONTRADICTIONS!B:B,"I-SECDEP",CONTRADICTIONS!N:N,"OPEN")

Sheet GATES
A1: Gate | B1: Definition | C1: Formula | D1: Result
A2: Quote_Compliance_% | B2: % of EDGES with Quote_Compliant=YES | C2: =IFERROR(COUNTIF(EDGES!J:J,"YES")/(COUNTA(EDGES!A:A)-1),0) | D2: =IF(D2>=0.7,"PASS","FAIL")
A3: Ingestion_Backlog | B3: Count of RECORD_ITEMS Requires_Ingestion=YES | C3: =COUNTIF(RECORD_ITEMS!Q:Q,"YES") | D3: =IF(D3=0,"PASS","FAIL")
A4: Holding_Text_Verified | B4: Count of AUTHORITIES Holding_Text_Verified=NO | C4: =COUNTIF(AUTHORITIES!N:N,"NO") | D4: =IF(D4=0,"PASS","FAIL")
A5: Open_Contradictions | B5: Count of CONTRADICTIONS Status=OPEN | C5: =COUNTIF(CONTRADICTIONS!N:N,"OPEN") | D5: =IF(D5=0,"PASS","FAIL")

Sheet DRAFTING_PACK
A1: Issue_ID | B1: Issue_Title | C1: Status | D1: Primary_Anchor_Edge_ID | E1: Primary_Anchor_Layer | F1: Primary_Anchor_Quote | G1: Primary_Anchor_Source | H1: Top_Contradiction_ID | I1: Contradiction_Short | J1: Anchor_Upgrade_Count | K1: Next_Action
A2: I-DAMAGES | B2: Damages proof / estimate vs payment / remediation invoices | C2: draft-safe | D2: E00016 | E2: EVIDENCE_ITEM | F2: SJ requires no genuine dispute of material fact. | H2: CON-001 | I2: Miami Mold letter says 'no proof of payment exists' while payment detail shows cash payment entry. | J2: 7 | K2: 1) Upgrade anchors (Quote_Compliant=YES). 2) Ingest required items. 3) Draft argument using Primary Anchor + Contradiction.
A3: I-SPOLIATION | B3: Washer/dryer disposal; adverse inference | C3: draft-safe | D3: E00066 | E3: ROA_SPINE | F3: Police Report #2019-00042552 documents Plaintiff's unauthorized removal and disposal of Defendant's property | J3: 3 | K3: 1) Upgrade anchors (Quote_Compliant=YES). 2) Ingest required items. 3) Draft argument using Primary Anchor + Contradiction.
A4: I-SECDEP | B4: §83.49 written notice compliance | C4: needs_record | D4: E00060 | E4: ROA_SPINE | F4: §83.49(3) notice; $4,200 itemized [dated 01/06/2018] | J4: 6 | K4: 1) Upgrade anchors (Quote_Compliant=YES). 2) Ingest required items. 3) Draft argument using Primary Anchor + Contradiction.

Sheet ISSUE_MATRIX
A1: Issue_ID | B1: Issue_Title | C1: Status | D1: Support_Rank | E1: Best_Support_Edge_ID | F1: From | G1: Relation_Type | H1: Layer | I1: Quote_Compliant | J1: Evidence_Quote_Verbatim | K1: Evidence_Summary | L1: Evidence_RecordItem_IDs | M1: Notes
A2: I-DAMAGES | B2: Damages proof / estimate vs payment / remediation invoices | C2: draft-safe | D2: 1 | E2: E00016 | F2: Rule 1.510 | G2: SUPPORTS_ISSUE | H2: EVIDENCE_ITEM | I2: YES | J2: SJ requires no genuine dispute of material fact.
A3: I-DAMAGES | B3: Damages proof / estimate vs payment / remediation invoices | C3: draft-safe | D3: 2 | E3: E00010 | F3: Drimmer estimate label line | G3: SUPPORTS_ISSUE | H3: EVIDENCE_ITEM | I3: NO | K3: ESTIMATE | L3: ROA-TXT-1336
A4: I-DAMAGES | B4: Damages proof / estimate vs payment / remediation invoices | C4: draft-safe | D4: 3 | E4: E00011 | F4: Miami Mold payment detail lines (amount/method/invoice) | G4: SUPPORTS_ISSUE | H4: EVIDENCE_ITEM | I4: NO | K4: pt for Payment Amount: $6,500,00 | f nns;ic1ion rmte: 01i2'1!201 a Mc1hod oi payncnt: Ca.sh | Payricnl ol Invoice #80623 | L4: ROA-TXT-17966
A5: I-SPOLIATION | B5: Washer/dryer disposal; adverse inference | C5: draft-safe | D5: 1 | E5: E00066 | F5: Police Report #2019-00042552 | G5: SUPPORTS_ISSUE | H5: ROA_SPINE | I5: YES | J5: Police Report #2019-00042552 documents Plaintiff's unauthorized removal and disposal of Defendant's property | M5: Imported from JSON
A6: I-SPOLIATION | B6: Washer/dryer disposal; adverse inference | C6: draft-safe | D6: 2 | E6: E00013 | F6: Defendants' Reply assertion re police report disposal | G6: SUPPORTS_ISSUE | H6: MOTION_ASSERTION | I6: YES | J6: Police Report #2019-00042552 documents Plaintiff's unauthorized removal and disposal of Defendant's property .. | L6: ROA-TXT-18011
A7: I-SPOLIATION | B7: Washer/dryer disposal; adverse inference | C7: draft-safe | D7: 3 | E7: E00014 | F7: Defendants' Reply reliance on Valcin for adverse inference | G7: SUPPORTS_ISSUE | H7: MOTION_ASSERTION | I7: YES | J7: Under Public Health Trust v. Valcin, 507 So. 2d 596 (Fla. 1987), this mandates an adverse inference. | L7: ROA-TXT-18017
A8: I-SECDEP | B8: §83.49 written notice compliance | C8: needs_record | D8: 1 | E8: E00060 | F8: E-SEC-01 | G8: SUPPORTS_ISSUE | H8: ROA_SPINE | I8: YES | J8: §83.49(3) notice; $4,200 itemized [dated 01/06/2018] | M8: Imported from JSON
A9: I-SECDEP | B9: §83.49 written notice compliance | C9: needs_record | D9: 2 | E9: E00008 | F9: Security deposit notice title line | G9: SUPPORTS_ISSUE | H9: EVIDENCE_ITEM | I9: YES | J9: NOTICE OF INTENTION TO IMPOSE CLAIM ON SECURITY DEPOSIT | L9: ROA-TXT-5960
A10: I-SECDEP | B10: §83.49 written notice compliance | C10: needs_record | D10: 3 | E10: E00009 | F10: Security deposit notice date line | G10: SUPPORTS_ISSUE | H10: EVIDENCE_ITEM | I10: NO | K10: DATE: January 6th, 2018 | L10: ROA-TXT-5962

Sheet CONTRADICTION_BRIEF
A1: Conflict_ID | B1: Issue_ID | C1: Issue_Title | D1: Conflict_Type | E1: Impact | F1: Use_Mode | G1: Status | H1: Item_A | I1: Layer_A | J1: A_Quote_Verbatim | K1: A_Source_Location | L1: Item_B | M1: Layer_B | N1: B_Quote_Verbatim | O1: B_Source_Location | P1: Resolution_Path
A2: CON-001 | B2: I-DAMAGES | C2: Damages proof / estimate vs payment / remediation invoices | D2: record-vs-record | E2: High | F2: exploit | G2: OPEN | H2: ROA-TXT-16626 | I2: EVIDENCE_ITEM | J2: ~o proof of payment exists of the S6.500.UO cash paymentthat Eli Cohen made tu Miami \fold LLC for mold remediation pcrfoHrn:d at his apartmc:nt located at: 1000 South Pointe Drive. Unit TI-f-/\5, Miami Beach, Fl, 33139 other than invoice # | K2: DOC-ROA-TXT@L16626 | L2: ROA-TXT-17966 | M2: EVIDENCE_ITEM | N2: pt for Payment Amount: $6,500,00 | f nns;ic1ion rmte: 01i2'1!201 a Mc1hod oi payncnt: Ca.sh | Payricnl ol Invoice #80623 | O2: DOC-ROA-TXT@L17966-L17968 | P2: Frame as internal record conflict; argue dispute/credibility; avoid categorical statements.

Sheet ANCHOR_UPGRADE
A1: Edge_ID | B1: Layer | C1: From_Entity_ID | D1: From_Name | E1: To_Entity_ID | F1: To_Name | G1: Relation_Type | H1: Evidence_RecordItem_IDs | I1: Evidence_Summary | J1: Suggested_Next_Step
A2: E00002 | B2: ROA_SPINE | C2: DOC-ROA-TXT | D2: Record - Record on Appeal.txt | E2: ROA-TXT-5962 | F2: Security deposit notice date line | G2: CONTAINS | H2: ROA-TXT-5962 | I2: DATE: January 6th, 2018 | J2: Find 8–20 word verbatim quote in ROA; add RecordItem + relink.
A3: E00003 | B3: ROA_SPINE | C3: DOC-ROA-TXT | D3: Record - Record on Appeal.txt | E3: ROA-TXT-1336 | F3: Drimmer estimate label line | G3: CONTAINS | H3: ROA-TXT-1336 | I3: ESTIMATE | J3: Find 8–20 word verbatim quote in ROA; add RecordItem + relink.
A4: E00004 | B4: ROA_SPINE | C4: DOC-ROA-TXT | D4: Record - Record on Appeal.txt | E4: ROA-TXT-17966 | F4: Miami Mold payment detail lines (amount/method/invoice) | G4: CONTAINS | H4: ROA-TXT-17966 | I4: pt for Payment Amount: $6,500,00 | f nns;ic1ion rmte: 01i2'1!201 a Mc1hod oi payncnt: Ca.sh | Payricnl ol Invoice #80623 | J4: Find 8–20 word verbatim quote in ROA; add RecordItem + relink.
A5: E00005 | B5: ROA_SPINE | C5: DOC-ROA-TXT | D5: Record - Record on Appeal.txt | E5: ROA-TXT-16626 | F5: Miami Mold June 3, 2019 letter re: proof of payment | G5: CONTAINS | H5: ROA-TXT-16626 | I5: ~o proof of payment exists of the S6.500.UO cash paymentthat Eli Cohen made tu Miami \fold LLC for mold remediation pcrfoHrn:d at his apartmc:nt located at: 1000 South Pointe Drive. Unit TI-f-/\5, Miami Beach, Fl, 33139 other than invoice # | J5: Find 8–20 word verbatim quote in ROA; add RecordItem + relink.
A6: E00009 | B6: EVIDENCE_ITEM | C6: ROA-TXT-5962 | D6: Security deposit notice date line | E6: I-SECDEP | F6: §83.49 written notice compliance | G6: SUPPORTS_ISSUE | H6: ROA-TXT-5962 | I6: DATE: January 6th, 2018 | J6: Find 8–20 word verbatim quote in ROA; add RecordItem + relink.
A7: E00010 | B7: EVIDENCE_ITEM | C7: ROA-TXT-1336 | D7: Drimmer estimate label line | E7: I-DAMAGES | F7: Damages proof / estimate vs payment / remediation invoices | G7: SUPPORTS_ISSUE | H7: ROA-TXT-1336 | I7: ESTIMATE | J7: Find 8–20 word verbatim quote in ROA; add RecordItem + relink.
A8: E00011 | B8: EVIDENCE_ITEM | C8: ROA-TXT-17966 | D8: Miami Mold payment detail lines (amount/method/invoice) | E8: I-DAMAGES | F8: Damages proof / estimate vs payment / remediation invoices | G8: SUPPORTS_ISSUE | H8: ROA-TXT-17966 | I8: pt for Payment Amount: $6,500,00 | f nns;ic1ion rmte: 01i2'1!201 a Mc1hod oi payncnt: Ca.sh | Payricnl ol Invoice #80623 | J8: Find 8–20 word verbatim quote in ROA; add RecordItem + relink.
A9: E00012 | B9: EVIDENCE_ITEM | C9: ROA-TXT-16626 | D9: Miami Mold June 3, 2019 letter re: proof of payment | E9: I-DAMAGES | F9: Damages proof / estimate vs payment / remediation invoices | G9: SUPPORTS_ISSUE | H9: ROA-TXT-16626 | I9: ~o proof of payment exists of the S6.500.UO cash paymentthat Eli Cohen made tu Miami \fold LLC for mold remediation pcrfoHrn:d at his apartmc:nt located at: 1000 South Pointe Drive. Unit TI-f-/\5, Miami Beach, Fl, 33139 other than invoice # | J9: Find 8–20 word verbatim quote in ROA; add RecordItem + relink.
A10: E00015 | B10: EVIDENCE_ITEM | C10: AUTH-FL-VALCIN | D10: Valcin | E10: I-SPOLIATION | F10: Washer/dryer disposal; adverse inference | G10: SUPPORTS_ISSUE | I10: [PROPOSITION_PENDING] | J10: Find 8–20 word verbatim quote in ROA; add RecordItem + relink.
A11: E00018 | B11: EVIDENCE_ITEM | C11: CLM-DAM-001 | D11: Drimmer document is labeled ESTIMATE (not proof of payment). | E11: ROA-TXT-1336 | F11: Drimmer estimate label line | G11: EVIDENCED_BY | H11: ROA-TXT-1336 | I11: ESTIMATE | J11: Find 8–20 word verbatim quote in ROA; add RecordItem + relink.
A12: E00020 | B12: EVIDENCE_ITEM | C12: CLM-DAM-002 | D12: Miami Mold materials contain both 'no proof of payment' language and a payment e | E12: ROA-TXT-16626 | F12: Miami Mold June 3, 2019 letter re: proof of payment | G12: EVIDENCED_BY | H12: ROA-TXT-16626 | I12: ~o proof of payment exists of the S6.500.UO cash paymentthat Eli Cohen made tu Miami \fold LLC for mold remediation pcrfoHrn:d at his apartmc:nt located at: 1000 South Pointe Drive. Unit TI-f-/\5, Miami Beach, Fl, 33139 other than invoice # | J12: Find 8–20 word verbatim quote in ROA; add RecordItem + relink.
A13: E00021 | B13: EVIDENCE_ITEM | C13: CLM-DAM-002 | D13: Miami Mold materials contain both 'no proof of payment' language and a payment e | E13: ROA-TXT-17966 | F13: Miami Mold payment detail lines (amount/method/invoice) | G13: EVIDENCED_BY | H13: ROA-TXT-17966 | I13: pt for Payment Amount: $6,500,00 | f nns;ic1ion rmte: 01i2'1!201 a Mc1hod oi payncnt: Ca.sh | Payricnl ol Invoice #80623 | J13: Find 8–20 word verbatim quote in ROA; add RecordItem + relink.
A14: E00026 | B14: EVIDENCE_ITEM | C14: CLM-SPO-002 | D14: Valcin adverse inference principle (proposition pending). | E14: AUTH-FL-VALCIN | F14: Valcin | G14: SUPPORTED_BY | I14: [PROPOSITION_PENDING] | J14: Find 8–20 word verbatim quote in ROA; add RecordItem + relink.
A15: E00028 | B15: EVIDENCE_ITEM | C15: CON-001 | D15: Miami Mold letter says 'no proof of payment exists' while payment detail shows c | E15: ROA-TXT-16626 | F15: Miami Mold June 3, 2019 letter re: proof of payment | G15: INVOLVES | H15: ROA-TXT-16626 | I15: ~o proof of payment exists of the S6.500.UO cash paymentthat Eli Cohen made tu Miami \fold LLC for mold remediation pcrfoHrn:d at his apartmc:nt located at: 1000 South Pointe Drive. Unit TI-f-/\5, Miami Beach, Fl, 33139 other than invoice # | J15: Find 8–20 word verbatim quote in ROA; add RecordItem + relink.
A16: E00029 | B16: EVIDENCE_ITEM | C16: CON-001 | D16: Miami Mold letter says 'no proof of payment exists' while payment detail shows c | E16: ROA-TXT-17966 | F16: Miami Mold payment detail lines (amount/method/invoice) | G16: INVOLVES | H16: ROA-TXT-17966 | I16: pt for Payment Amount: $6,500,00 | f nns;ic1ion rmte: 01i2'1!201 a Mc1hod oi payncnt: Ca.sh | Payricnl ol Invoice #80623 | J16: Find 8–20 word verbatim quote in ROA; add RecordItem + relink.
A17: E00037 | B17: ROA_SPINE | C17: JEFF_ATLAS | D17: JEFF ATLAS | E17: 2020-000746-CA-01 | F17: 2020-000746-CA-01 | G17: DEFENDANT_IN | I17: Defendant ATLAS, JEFF | J17: Find 8–20 word verbatim quote in ROA; add RecordItem + relink.
A18: E00038 | B18: ROA_SPINE | C18: SUSAN_ATLAS | D18: SUSAN ATLAS | E18: 2020-000746-CA-01 | F18: 2020-000746-CA-01 | G18: DEFENDANT_IN | I18: Defendant ATLAS, SUSAN | J18: Find 8–20 word verbatim quote in ROA; add RecordItem + relink.
A19: E00042 | B19: ROA_SPINE | C19: David_B_Haber | D19: David B. Haber | E19: HABER_LAW_LLP | F19: HABER LAW, LLP | G19: PARTNER_AT | I19: David Brian Haber: dhaber@haber.law | J19: Find 8–20 word verbatim quote in ROA; add RecordItem + relink.
A20: E00043 | B20: ROA_SPINE | C20: Thomas_Butler | D20: Thomas Butler | E20: JEFF_ATLAS | F20: JEFF ATLAS | G20: FORMER_COUNSEL_FOR | I20: Defendant ATLAS, JEFF B#: 569178 Thomas Butler | J20: Find 8–20 word verbatim quote in ROA; add RecordItem + relink.
A21: E00044 | B21: ROA_SPINE | C21: Judge_Reemberto_Diaz | D21: Judge Reemberto Diaz | E21: 2020-000746-CA-01 | F21: 2020-000746-CA-01 | G21: PRESIDES_OVER | I21: Judicial Section: CA30 - Downtown Miami - JudgeDiaz, Reemberto | J21: Find 8–20 word verbatim quote in ROA; add RecordItem + relink.
A22: E00062 | B22: ROA_SPINE | C22: E-WASH-01 | D22: E-WASH-01 | E22: I-MAINT | F22: I-MAINT | G22: SUPPORTS_ISSUE | I22: Atlas purchased before lease [dated 2017] | J22: Find 8–20 word verbatim quote in ROA; add RecordItem + relink.
A23: E00063 | B23: ROA_SPINE | C23: E-CHW-01 | D23: E-CHW-01 | E23: I-MISREP | F23: I-MISREP | G23: SUPPORTS_ISSUE | I23: Denials for pre-existing conditions [2018-2019] | J23: Find 8–20 word verbatim quote in ROA; add RecordItem + relink.
A24: E00071 | B24: ROA_SPINE | C24: 05_18_2018 | D24: 05/18/2018 | E24: 2018-011311-CC-05 | F24: 2018-011311-CC-05 | G24: FILED_ON | I24: Filing Date: 05/18/2018 | J24: Find 8–20 word verbatim quote in ROA; add RecordItem + relink.
A25: E00074 | B25: ROA_SPINE | C25: 01_14_2020 | D25: 01/14/2020 | E25: 2020-000746-CA-01 | F25: 2020-000746-CA-01 | G25: FILED_ON | I25: Filing Date: 01/14/2020 | J25: Find 8–20 word verbatim quote in ROA; add RecordItem + relink.
A26: E00080 | B26: MOTION_ASSERTION | C26: REPLY-A1 | D26: REPLY-A1 | E26: Fla_R_Civ_P_1510 | F26: Fla. R. Civ. P. 1.510 | G26: CITES_RULE | I26: Plaintiff fails to meet their burden under Fla. R. Civ. P. 1.510. The revised federal-aligned standard requires specific, admissible evidence demonstrating a genuine dispute of material fact. | J26: Find 8–20 word verbatim quote in ROA; add RecordItem + relink.
A27: E00087 | B27: MOTION_ASSERTION | C27: REPLY-A8 | D27: REPLY-A8 | E27: I-DAMAGES | F27: Damages proof / estimate vs payment / remediation invoices | G27: ATTACKS | I27: Plaintiff's allegations rely on nothing more than unpaid estimates for a washer dryer and unsupported invoices for the alleged remediation, offering no proof of actual payment. | J27: Find 8–20 word verbatim quote in ROA; add RecordItem + relink.
A28: E00091 | B28: MOTION_ASSERTION | C28: REPLY-A12 | D28: REPLY-A12 | E28: DIN-169 | F28: CIR-169 / DIN 169 | G28: PRECEDES | I28: Having failed to provide competent evidence and having destroyed key evidence, Plaintiff cannot avoid summary judgment. As a matter of law, it must be granted. | J28: Find 8–20 word verbatim quote in ROA; add RecordItem + relink.
... A55: E00131 | B55: COURT_FINDING | C55: DIN-169 | D55: CIR-169 / DIN 169 | E55: 2020-000746-CA-01 | F55: 2020-000746-CA-01 | G55: JUDGMENT_IN | I55: Record_Pages: 1341-1354 | J55: Find 8–20 word verbatim quote in ROA; add RecordItem + relink.

Sheet INGESTION_QUEUE
A1: RecordItem_ID | B1: Description | C1: Evidence_Class | D1: Requires_Ingestion | E1: Source_Location | F1: Tags | G1: Suggested_Action | H1: Priority
A2: ROA-TXT-18011 | B2: Defendants' Reply assertion re police report disposal | C2: Evidence_Reference | D2: YES | E2: DOC-ROA-TXT@L18011 | F2: spoliation;police report;2019-00042552;motion assertion | G2: Ingest underlying exhibit text/pages; then convert to Evidence_Item and add quote-verbatim anchor. | H2: P1
A3: ROA-TXT-18017 | B3: Defendants' Reply reliance on Valcin for adverse inference | C3: Evidence_Reference | D3: YES | E3: DOC-ROA-TXT@L18017 | F3: spoliation;Valcin;adverse inference;motion assertion | G3: Ingest underlying exhibit text/pages; then convert to Evidence_Item and add quote-verbatim anchor. | H3: P1

Sheet EDGE_BUILDER
A1: From_Entity_ID | B1: To_Entity_ID | C1: Relation_Type | D1: Layer | E1: Evidence_RecordItem_ID | F1: Evidence_Authority_ID | G1: Evidence_Quote_Verbatim | H1: Quote_WC | I1: Quote_Compliant | J1: Notes | K1: Action
G2: =IF($E2="","",VLOOKUP($E2,RECORD_ITEMS!$A:$T,6,FALSE)) | H2: =IF($G2="","",LEN(TRIM($G2))-LEN(SUBSTITUTE(TRIM($G2)," ",""))+1) | I2: =IF($H2="","",IF(AND($H2>=8,$H2<=20),"YES","NO")) | K2: =IF($A2="","",IF($I2="YES","READY_TO_COPY","UPGRADE_ANCHOR"))
G3: =IF($E3="","",VLOOKUP($E3,RECORD_ITEMS!$A:$T,6,FALSE)) | H3: =IF($G3="","",LEN(TRIM($G3))-LEN(SUBSTITUTE(TRIM($G3)," ",""))+1) | I3: =IF($H3="","",IF(AND($H3>=8,$H3<=20),"YES","NO")) | K3: =IF($A3="","",IF($I3="YES","READY_TO_COPY","UPGRADE_ANCHOR"))
G4: =IF($E4="","",VLOOKUP($E4,RECORD_ITEMS!$A:$T,6,FALSE)) | H4: =IF($G4="","",LEN(TRIM($G4))-LEN(SUBSTITUTE(TRIM($G4)," ",""))+1) | I4: =IF($H4="","",IF(AND($H4>=8,$H4<=20),"YES","NO")) | K4: =IF($A4="","",IF($I4="YES","READY_TO_COPY","UPGRADE_ANCHOR"))
G5: =IF($E5="","",VLOOKUP($E5,RECORD_ITEMS!$A:$T,6,FALSE)) | H5: =IF($G5="","",LEN(TRIM($G5))-LEN(SUBSTITUTE(TRIM($G5)," ",""))+1) | I5: =IF($H5="","",IF(AND($H5>=8,$H5<=20),"YES","NO")) | K5: =IF($A5="","",IF($I5="YES","READY_TO_COPY","UPGRADE_ANCHOR"))
G6: =IF($E6="","",VLOOKUP($E6,RECORD_ITEMS!$A:$T,6,FALSE)) | H6: =IF($G6="","",LEN(TRIM($G6))-LEN(SUBSTITUTE(TRIM($G6)," ",""))+1) | I6: =IF($H6="","",IF(AND($H6>=8,$H6<=20),"YES","NO")) | K6: =IF($A6="","",IF($I6="YES","READY_TO_COPY","UPGRADE_ANCHOR"))
G7: =IF($E7="","",VLOOKUP($E7,RECORD_ITEMS!$A:$T,6,FALSE)) | H7: =IF($G7="","",LEN(TRIM($G7))-LEN(SUBSTITUTE(TRIM($G7)," ",""))+1) | I7: =IF($H7="","",IF(AND($H7>=8,$H7<=20),"YES","NO")) | K7: =IF($A7="","",IF($I7="YES","READY_TO_COPY","UPGRADE_ANCHOR"))
G8: =IF($E8="","",VLOOKUP($E8,RECORD_ITEMS!$A:$T,6,FALSE)) | H8: =IF($G8="","",LEN(TRIM($G8))-LEN(SUBSTITUTE(TRIM($G8)," ",""))+1) | I8: =IF($H8="","",IF(AND($H8>=8,$H8<=20),"YES","NO")) | K8: =IF($A8="","",IF($I8="YES","READY_TO_COPY","UPGRADE_ANCHOR"))
G9: =IF($E9="","",VLOOKUP($E9,RECORD_ITEMS!$A:$T,6,FALSE)) | H9: =IF($G9="","",LEN(TRIM($G9))-LEN(SUBSTITUTE(TRIM($G9)," ",""))+1) | I9: =IF($H9="","",IF(AND($H9>=8,$H9<=20),"YES","NO")) | K9: =IF($A9="","",IF($I9="YES","READY_TO_COPY","UPGRADE_ANCHOR"))
G10: =IF($E10="","",VLOOKUP($E10,RECORD_ITEMS!$A:$T,6,FALSE)) | H10: =IF($G10="","",LEN(TRIM($G10))-LEN(SUBSTITUTE(TRIM($G10)," ",""))+1) | I10: =IF($H10="","",IF(AND($H10>=8,$H10<=20),"YES","NO")) | K10: =IF($A10="","",IF($I10="YES","READY_TO_COPY","UPGRADE_ANCHOR"))
G11: =IF($E11="","",VLOOKUP($E11,RECORD_ITEMS!$A:$T,6,FALSE)) | H11: =IF($G11="","",LEN(TRIM($G11))-LEN(SUBSTITUTE(TRIM($G11)," ",""))+1) | I11: =IF($H11="","",IF(AND($H11>=8,$H11<=20),"YES","NO")) | K11: =IF($A11="","",IF($I11="YES","READY_TO_COPY","UPGRADE_ANCHOR"))
G12: =IF($E12="","",VLOOKUP($E12,RECORD_ITEMS!$A:$T,6,FALSE)) | H12: =IF($G12="","",LEN(TRIM($G12))-LEN(SUBSTITUTE(TRIM($G12)," ",""))+1) | I12: =IF($H12="","",IF(AND($H12>=8,$H12<=20),"YES","NO")) | K12: =IF($A12="","",IF($I12="YES","READY_TO_COPY","UPGRADE_ANCHOR"))
G13: =IF($E13="","",VLOOKUP($E13,RECORD_ITEMS!$A:$T,6,FALSE)) | H13: =IF($G13="","",LEN(TRIM($G13))-LEN(SUBSTITUTE(TRIM($G13)," ",""))+1) | I13: =IF($H13="","",IF(AND($H13>=8,$H13<=20),"YES","NO")) | K13: =IF($A13="","",IF($I13="YES","READY_TO_COPY","UPGRADE_ANCHOR"))
... G201: =IF($E201="","",VLOOKUP($E201,RECORD_ITEMS!$A:$T,6,FALSE)) | H201: =IF($G201="","",LEN(TRIM($G201))-LEN(SUBSTITUTE(TRIM($G201)," ",""))+1) | I201: =IF($H201="","",IF(AND($H201>=8,$H201<=20),"YES","NO")) | K201: =IF($A201="","",IF($I201="YES","READY_TO_COPY","UPGRADE_ANCHOR"))

Sheet LISTS
A1: Entity_IDs | B1: RecordItem_IDs | C1: Authority_IDs | D1: Relation_Types | E1: Layers
A2: 01_06_2018 | B2: ROA-TXT-1336 | C2: AUTH-FL-RULE-1510 | D2: CONTAINS | E2: ROA_SPINE
A3: 01_14_2020 | B3: ROA-TXT-16626 | C3: AUTH-FL-VALCIN | D3: SUPPORTS_ISSUE | E3: COURT_FINDING
A4: 05_18_2018 | B4: ROA-TXT-17966 | D4: EVIDENCED_BY | E4: MOTION_ASSERTION
A5: 08_02_2025 | B5: ROA-TXT-18011 | D5: SUPPORTED_BY | E5: EVIDENCE_ITEM
A6: 09_02_2025 | B6: ROA-TXT-18017 | D6: CITED_IN | E6: EVIDENCE_REFERENCE
A7: 12562763 | B7: ROA-TXT-5960 | D7: ENTERED_BY
A8: 1272649 | B8: ROA-TXT-5962 | D8: FILED_BY
A9: 12_22_2017 | D9: ORDER_IN
A10: 15000 | D10: HEARING_ON
A11: 2018-011311-CC-05 | D11: CONTRADICTED_BY
A12: 2020-000746-CA-01 | D12: CONTRADICTS
A13: 3D25-1676 | D13: AFFECTS
A14: AD-1-REJECTED | D14: INVOLVES
A15: AD-2-REJECTED | D15: BLOCKS
A16: AD-3-REJECTED | D16: RELATES_TO
A17: AD-4-REJECTED | D17: GOVERNS
A18: AD-5-REJECTED | D18: DATED
A19: AD-6-REJECTED | D19: FILED_ON
A20: AD-7-REJECTED | D20: ENTERED_ON
... A25: CIR-126 | D25: COUNSEL_FOR
A26: CIR-135/DIN135
A27: CIR-142
A28: CIR-148/DIN148
A29: CIR-151/DIN151
A30: CIR-158/DIN158
A31: CIR-161/DIN161
A32: CIR-164/DIN164
A33: CIR-169/DIN169
A34: CIR-170/DIN170
A35: CIR-173/DIN173
A36: CIR-176/DIN176
A37: CIR-178/DIN178
... A140: Wootton_v_Iron_Acquisitions_LLC_338_So_3d_425_Fla_2d_DCA_2022

Sheet README
A1: CUARC Entity Map / Matrix for Cohen v. Atlas
A3: Purpose
A4: This workbook is a structured entity database to normalize record fragments, authorities, claims, and issue-level arguments. It is designed to reduce clutter when pulling from other projects by forcing each imported statement into typed, citable objects (CUARC).
A6: Core objects
A7: RECORD_ITEMS: quote-ready snippets with precise locations and tags.
A8: AUTHORITIES: the master authority table (schema provided by user).
A9: CLAIMS: typed propositions (T1–T5) linked to record items and authorities.
A10: ISSUES: appellate issue buckets + risk and remedy target.
A11: CONTRADICTIONS: explicit conflicts to exploit or reconcile.
A12: TASKS: missing items to ingest / verify.
A14: CUARC typing
A15: T1 fact → RecordItems; T2 rule → Authorities; T3 label → Record+Authority; T4 inference → Record+Authority; T5 remedy → Authority+predicate Record.
... A27: GATES: binary health checks (quote compliance %, ingestion backlog, holding-text verification, open contradictions).

Sheet DOCUMENTS
A1: Doc_ID | B1: Filename | C1: Path | D1: Type | E1: Date_Added | F1: Notes
A2: DOC-ROA-PDF | B2: Record - Record on Appeal.pdf | C2: /mnt/data/Record - Record on Appeal.pdf | D2: Record on Appeal | E2: 2025-12-27
A3: DOC-ROA-TXT | B3: Record - Record on Appeal.txt | C3: /mnt/data/Record - Record on Appeal.txt | D3: Record on Appeal (text) | E3: 2025-12-27
A4: DOC-INITIAL-BRIEF | B4: COHEN_INITIAL_BRIEF_AESTHETIC_FINAL.pdf | C4: /mnt/data/COHEN_INITIAL_BRIEF_AESTHETIC_FINAL.pdf | D4: Brief | E4: 2025-12-27

Sheet AUTHORITIES
A1: AUTH_ID | B1: Type | C1: Citation | D1: Short_Cite | E1: Jurisdiction | F1: Court_Level | G1: Binding_Weight | H1: Proposition | I1: Stance_For_Appellant | J1: Linked_Issues | K1: Verified | L1: Notes | M1: Citation_Verified | N1: Holding_Text_Verified | O1: Holding_Text_Source | P1: Citation_Source_Location
A2: AUTH-FL-VALCIN | B2: Case | C2: Public Health Trust v. Valcin, 507 So. 2d 596 (Fla. 1987) | D2: Valcin | E2: Florida | F2: Supreme_Court | G2: 1 | H2: [PROPOSITION_PENDING] | I2: 0.9 | J2: I-SPOLIATION | K2: RECORD | L2: ROA cites Valcin; holding text requires approved source. | M2: RECORD | N2: NO
A3: AUTH-FL-RULE-1510 | B3: Rule | C3: Fla. R. Civ. P. 1.510 (Summary Judgment) (as adopted/updated) | D3: Rule 1.510 | E3: Florida | F3: Rule | G3: 1 | H3: SJ requires no genuine dispute of material fact. | I3: 0.5 | J3: I-DAMAGES;I-SJ | K3: UNVERIFIED_AUTHORITY | L3: Add approved rule text excerpt to authority table for court-ready quoting. | M3: UNVERIFIED_AUTHORITY | N3: NO

Sheet RECORD_ITEMS
A1: RecordItem_ID | B1: Source_Doc_ID | C1: Location | D1: Doc_Type | E1: Description | F1: Evidence_Quote_Verbatim | G1: Tags | H1: Party | I1: Date | J1: CUARC_Type | K1: Confidence | L1: Notes | M1: Evidence_Summary | N1: Quote_WC | O1: Quote_Verified | P1: Source_Layer | Q1: Source_Location | R1: Evidence_Class | S1: Requires_Ingestion | T1: Canonical_Entity_ID
A2: ROA-TXT-5960 | B2: DOC-ROA-TXT | C2: L5960 | D2: Exhibit/Notice | E2: Security deposit notice title line | F2: NOTICE OF INTENTION TO IMPOSE CLAIM ON SECURITY DEPOSIT | G2: 83.49;security deposit;notice | H2: Unknown | I2: 2018-01-06 (see L5962) | J2: T1 | K2: High | L2: Title indicates written notice exists. | N2: 9 | O2: UNREVIEWED | P2: EVIDENCE_ITEM | Q2: DOC-ROA-TXT@L5960 | R2: Evidence_Item | S2: NO
A3: ROA-TXT-5962 | B3: DOC-ROA-TXT | C3: L5962 | D3: Exhibit/Notice | E3: Security deposit notice date line | F3: DATE: January 6th, 2018 | G3: 83.49;security deposit;notice;date | H3: Unknown | I3: 2018-01-06 | J3: T1 | K3: High | L3: Use to contradict 'no written notice' assertion. | N3: 4 | O3: UNREVIEWED | P3: EVIDENCE_ITEM | Q3: DOC-ROA-TXT@L5962 | R3: Evidence_Item | S3: NO
A4: ROA-TXT-1336 | B4: DOC-ROA-TXT | C4: L1336 | D4: Exhibit/Estimate | E4: Drimmer estimate label line | F4: ESTIMATE | G4: damages;washer dryer;estimate | H4: Unknown | J4: T1 | K4: Medium | L4: Locate full Drimmer exhibit in PDF for cleaner quote. | N4: 1 | O4: UNREVIEWED | P4: EVIDENCE_ITEM | Q4: DOC-ROA-TXT@L1336 | R4: Evidence_Item | S4: NO
A5: ROA-TXT-17966 | B5: DOC-ROA-TXT | C5: L17966-L17968 | D5: Exhibit/Invoice/Payment | E5: Miami Mold payment detail lines (amount/method/invoice) | F5: pt for Payment Amount: $6,500,00 | f nns;ic1ion rmte: 01i2'1!201 a Mc1hod oi payncnt: Ca.sh | Payricnl ol Invoice #80623 | G5: damages;remediation;payment;Miami Mold;invoice 80623 | H5: Eli Cohen | I5: 2018-01-21? (see transaction line) | J5: T1 | K5: Medium | L5: Shows Payment Amount and method 'Cash' + Invoice #80623 (OCR garble). | N5: 20 | O5: UNREVIEWED | P5: EVIDENCE_ITEM | Q5: DOC-ROA-TXT@L17966-L17968 | R5: Evidence_Item | S5: NO
A6: ROA-TXT-16626 | B6: DOC-ROA-TXT | C6: L16626 | D6: Exhibit/Letter | E6: Miami Mold June 3, 2019 letter re: proof of payment | F6: ~o proof of payment exists of the S6.500.UO cash paymentthat Eli Cohen made tu Miami \fold LLC for mold remediation pcrfoHrn:d at his apartmc:nt located at: 1000 South Pointe Drive. Unit TI-f-/\5, Miami Beach, Fl, 33139 other than invoice # | G6: damages;remediation;payment dispute;Miami Mold | H6: Miami Mold Specialist, LLC | I6: 2019-06-03 | J6: T1 | K6: Medium | L6: Contains 'no proof of payment exists...' language; conflicts with payment detail. | N6: 40 | O6: UNREVIEWED | P6: EVIDENCE_ITEM | Q6: DOC-ROA-TXT@L16626 | R6: Evidence_Item | S6: NO
A7: ROA-TXT-18011 | B7: DOC-ROA-TXT | C7: L18011 | D7: Motion/Reply | E7: Defendants' Reply assertion re police report disposal | F7: Police Report #2019-00042552 documents Plaintiff's unauthorized removal and disposal of Defendant's property .. | G7: spoliation;police report;2019-00042552;motion assertion | H7: Defendants | I7: 2025-02-10 | J7: T1 (motion assertion) | K7: Medium | L7: Must be framed as 'Defendants argued...' unless police report ingested. | N7: 13 | O7: UNREVIEWED | P7: MOTION_ASSERTION | Q7: DOC-ROA-TXT@L18011 | R7: Evidence_Reference | S7: YES
A8: ROA-TXT-18017 | B8: DOC-ROA-TXT | C8: L18017 | D8: Motion/Reply | E8: Defendants' Reply reliance on Valcin for adverse inference | F8: Under Public Health Trust v. Valcin, 507 So. 2d 596 (Fla. 1987), this mandates an adverse inference. | G8: spoliation;Valcin;adverse inference;motion assertion | H8: Defendants | I8: 2025-02-10 | J8: T2/T4 (authority cited in motion) | K8: High | L8: Valcin citation appears; holding text must come from approved authority source. | N8: 17 | O8: UNREVIEWED | P8: MOTION_ASSERTION | Q8: DOC-ROA-TXT@L18017 | R8: Evidence_Reference | S8: YES

Sheet ISSUES
A1: Issue_ID | B1: Title | C1: Status | D1: Key_Risks | E1: Relief_Target | F1: Notes
A2: I-DAMAGES | B2: Damages proof / estimate vs payment / remediation invoices | C2: draft-safe | D2: Conflicting Miami Mold payment evidence; estimate-only line items | E2: damages-only (if predicate) | F2: Separate washer/dryer estimate from Miami Mold remediation payment conflict.
A3: I-SPOLIATION | B3: Washer/dryer disposal; adverse inference | C3: draft-safe | D3: Police report text not ingested; Valcin proposition pending in table | E3: adverse inference / sanctions / evidentiary inference | F3: Frame as argument unless underlying exhibit ingested.
A4: I-SECDEP | B4: §83.49 written notice compliance | C4: needs_record | D4: Order says no written notice; record appears to have notice | E4: liability-only (security deposit) | F4: Pull clean notice exhibit from PDF for quote.

Sheet CLAIMS
A1: Claim_ID | B1: Issue_ID | C1: Type | D1: Claim_Text | E1: RecordItem_IDs | F1: Authority_IDs | G1: Status | H1: Notes
A2: CLM-DAM-001 | B2: I-DAMAGES | C2: T1 | D2: Drimmer document is labeled ESTIMATE (not proof of payment). | E2: ROA-TXT-1336 | G2: PARTIAL | H2: Need cleaner exhibit quote from PDF; pair with Rule 1.510 authority.
A3: CLM-DAM-002 | B3: I-DAMAGES | C3: T1 | D3: Miami Mold materials contain both 'no proof of payment' language and a payment entry. | E3: ROA-TXT-16626;ROA-TXT-17966 | G3: CONFLICT | H3: Use as genuine dispute / credibility conflict; cannot assert 'no proof' as fact.
A4: CLM-SPO-001 | B4: I-SPOLIATION | C4: T1 (motion assertion) | D4: Defendants asserted police report documents unauthorized removal/disposal. | E4: ROA-TXT-18011 | G4: PARTIAL | H4: Needs police report itself to become T1 fact.
A5: CLM-SPO-002 | B5: I-SPOLIATION | C5: T2 | D5: Valcin adverse inference principle (proposition pending). | E5: ROA-TXT-18017 | F5: AUTH-FL-VALCIN | G5: PARTIAL | H5: Citation verified in record; need approved holding text excerpt for Proposition field.

Sheet CONTRADICTIONS
A1: Conflict_ID | B1: Issue_ID | C1: Item_A | D1: Item_B | E1: Description | F1: Impact | G1: Resolution_Path | H1: Conflict_Type | I1: Layer_A | J1: Layer_B | K1: Use_Mode | L1: Evidence_A_Verbatim | M1: Evidence_B_Verbatim | N1: Status
A2: CON-001 | B2: I-DAMAGES | C2: ROA-TXT-16626 | D2: ROA-TXT-17966 | E2: Miami Mold letter says 'no proof of payment exists' while payment detail shows cash payment entry. | F2: High | G2: Frame as internal record conflict; argue dispute/credibility; avoid categorical statements. | H2: record-vs-record | K2: exploit | N2: OPEN

Sheet TASKS
A1: Task_ID | B1: Priority | C1: Task | D1: Status | E1: Owner | F1: Due | G1: Notes
A2: HT-VALCIN-PROP | B2: P1 | C2: Populate Valcin proposition text from approved source (no web unless allowed). | D2: OPEN | G2: Authority row created; proposition pending.
A3: HT-POLICE-REPORT | B3: P1 | C3: Ingest Police Report #2019-00042552 into RecordItems with quote-ready excerpt. | D3: OPEN | G3: Current support is motion assertion / deposition reference only.
A4: HT-DRIMMER-PDF | B4: P1 | C4: Extract clean Drimmer exhibit quote (ESTIMATE/DELIVERY ONLY) from ROA PDF for use in brief. | D4: OPEN | G4: TXT has label but PDF likely cleaner.

Sheet ENTITIES
A1: Entity_ID | B1: Name | C1: Category | D1: Layer | E1: Canonical | F1: Definition_or_Context | G1: Source_Location | H1: Notes | I1: Canonical_Entity_ID
A2: DOC-ROA-PDF | B2: Record - Record on Appeal.pdf | C2: Document | D2: EVIDENCE_ITEM | E2: YES | F2: Record on Appeal | G2: /mnt/data/Record - Record on Appeal.pdf | I2: DOC-ROA-PDF
A3: DOC-ROA-TXT | B3: Record - Record on Appeal.txt | C3: Document | D3: EVIDENCE_ITEM | E3: YES | F3: Record on Appeal (text) | G3: /mnt/data/Record - Record on Appeal.txt | I3: DOC-ROA-TXT
A4: DOC-INITIAL-BRIEF | B4: COHEN_INITIAL_BRIEF_AESTHETIC_FINAL.pdf | C4: Document | D4: EVIDENCE_ITEM | E4: YES | F4: Brief | G4: /mnt/data/COHEN_INITIAL_BRIEF_AESTHETIC_FINAL.pdf | I4: DOC-INITIAL-BRIEF
A5: I-DAMAGES | B5: Damages proof / estimate vs payment / remediation invoices | C5: Issue | D5: ROA_SPINE | E5: YES | F5: draft-safe | H5: Conflicting Miami Mold payment evidence; estimate-only line items | Separate washer/dryer estimate from Miami Mold remediation payment conflict. | I5: I-DAMAGES
A6: I-SPOLIATION | B6: Washer/dryer disposal; adverse inference | C6: Issue | D6: ROA_SPINE | E6: YES | F6: draft-safe | H6: Police report text not ingested; Valcin proposition pending in table | Frame as argument unless underlying exhibit ingested. | I6: I-SPOLIATION
A7: I-SECDEP | B7: §83.49 written notice compliance | C7: Issue | D7: ROA_SPINE | E7: YES | F7: needs_record | H7: Order says no written notice; record appears to have notice | Pull clean notice exhibit from PDF for quote. | I7: I-SECDEP
A8: AUTH-FL-VALCIN | B8: Valcin | C8: Authority | D8: EVIDENCE_ITEM | E8: YES | F8: Public Health Trust v. Valcin, 507 So. 2d 596 (Fla. 1987) | H8: ROA cites Valcin; holding text requires approved source. | I8: AUTH-FL-VALCIN
A9: AUTH-FL-RULE-1510 | B9: Rule 1.510 | C9: Authority | D9: EVIDENCE_ITEM | E9: YES | F9: Fla. R. Civ. P. 1.510 (Summary Judgment) (as adopted/updated) | H9: Add approved rule text excerpt to authority table for court-ready quoting. | I9: AUTH-FL-RULE-1510
A10: ROA-TXT-5960 | B10: Security deposit notice title line | C10: Evidence_Item | D10: EVIDENCE_ITEM | E10: YES | F10: Exhibit/Notice | G10: DOC-ROA-TXT@L5960 | H10: 83.49;security deposit;notice | I10: ROA-TXT-5960
A11: ROA-TXT-5962 | B11: Security deposit notice date line | C11: Evidence_Item | D11: EVIDENCE_ITEM | E11: YES | F11: Exhibit/Notice | G11: DOC-ROA-TXT@L5962 | H11: 83.49;security deposit;notice;date | I11: ROA-TXT-5962
A12: ROA-TXT-1336 | B12: Drimmer estimate label line | C12: Evidence_Item | D12: EVIDENCE_ITEM | E12: YES | F12: Exhibit/Estimate | G12: DOC-ROA-TXT@L1336 | H12: damages;washer dryer;estimate | I12: ROA-TXT-1336
A13: ROA-TXT-17966 | B13: Miami Mold payment detail lines (amount/method/invoice) | C13: Evidence_Item | D13: EVIDENCE_ITEM | E13: YES | F13: Exhibit/Invoice/Payment | G13: DOC-ROA-TXT@L17966-L17968 | H13: damages;remediation;payment;Miami Mold;invoice 80623 | I13: ROA-TXT-17966
A14: ROA-TXT-16626 | B14: Miami Mold June 3, 2019 letter re: proof of payment | C14: Evidence_Item | D14: EVIDENCE_ITEM | E14: YES | F14: Exhibit/Letter | G14: DOC-ROA-TXT@L16626 | H14: damages;remediation;payment dispute;Miami Mold | I14: ROA-TXT-16626
A15: ROA-TXT-18011 | B15: Defendants' Reply assertion re police report disposal | C15: Evidence_Reference | D15: MOTION_ASSERTION | E15: YES | F15: Motion/Reply | G15: DOC-ROA-TXT@L18011 | H15: spoliation;police report;2019-00042552;motion assertion | I15: ROA-TXT-18011
A16: ROA-TXT-18017 | B16: Defendants' Reply reliance on Valcin for adverse inference | C16: Evidence_Reference | D16: MOTION_ASSERTION | E16: YES | F16: Motion/Reply | G16: DOC-ROA-TXT@L18017 | H16: spoliation;Valcin;adverse inference;motion assertion | I16: ROA-TXT-18017
A17: CLM-DAM-001 | B17: Drimmer document is labeled ESTIMATE (not proof of payment). | C17: Claim | D17: EVIDENCE_ITEM | E17: YES | F17: T1 | H17: PARTIAL | I17: CLM-DAM-001
A18: CLM-DAM-002 | B18: Miami Mold materials contain both 'no proof of payment' language and a payment e | C18: Claim | D18: EVIDENCE_ITEM | E18: YES | F18: T1 | H18: CONFLICT | I18: CLM-DAM-002
A19: CLM-SPO-001 | B19: Defendants asserted police report documents unauthorized removal/disposal. | C19: Claim | D19: EVIDENCE_ITEM | E19: YES | F19: T1 (motion assertion) | H19: PARTIAL | I19: CLM-SPO-001
A20: CLM-SPO-002 | B20: Valcin adverse inference principle (proposition pending). | C20: Claim | D20: EVIDENCE_ITEM | E20: YES | F20: T2 | H20: PARTIAL | I20: CLM-SPO-002
A21: CON-001 | B21: Miami Mold letter says 'no proof of payment exists' while payment detail shows c | C21: Contradiction | D21: EVIDENCE_ITEM | E21: YES | F21: record-vs-record | H21: Frame as internal record conflict; argue dispute/credibility; avoid categorical statements. | I21: CON-001
A22: HT-VALCIN-PROP | B22: Populate Valcin proposition text from approved source (no web unless allowed). | C22: Task | D22: ROA_SPINE | E22: YES | F22: P1 | H22: OPEN | I22: HT-VALCIN-PROP
A23: HT-POLICE-REPORT | B23: Ingest Police Report #2019-00042552 into RecordItems with quote-ready excerpt. | C23: Task | D23: ROA_SPINE | E23: YES | F23: P1 | H23: OPEN | I23: HT-POLICE-REPORT
A24: HT-DRIMMER-PDF | B24: Extract clean Drimmer exhibit quote (ESTIMATE/DELIVERY ONLY) from ROA PDF for us | C24: Task | D24: ROA_SPINE | E24: YES | F24: P1 | H24: OPEN | I24: HT-DRIMMER-PDF
A25: PTY-ELI-COHEN | B25: Eli Cohen | C25: Party | D25: ROA_SPINE | E25: YES | G25: DOC-ROA-TXT@L32 | H25: PLAINTIFF ELI COHEN'S EXHIBIT LIST 271 -274 | I25: PTY-ELI-COHEN
A26: PTY-JEFF-ATLAS | B26: Jeff Atlas | C26: Party | D26: ROA_SPINE | E26: YES | G26: DOC-ROA-TXT@L679 | H26: Plmntift ELI COHEN, anindividual, suesDefendants,JEFF ATLAS~ an individual,and SUSAN ATLAS, m1 individual,and alleges as follows: JURISDIC'J | I26: PTY-JEFF-ATLAS
A27: PTY-SUSAN-ATLAS | B27: Susan Atlas | C27: Party | D27: ROA_SPINE | E27: YES | G27: DOC-ROA-TXT@L155 | H27: PLAINTIFF'S, ELI COHEN, MOTION FOR SUMMARY JUDGMENT AS TO ALL COUNTS AGAINST DEFENDANTS, JEFF AND SUSAN ATLAS 1,137-1,301 | I27: PTY-SUSAN-ATLAS
A28: 2020-000746-CA-01 | B28: 2020-000746-CA-01 | C28: Case | D28: ROA_SPINE | E28: YES | F28: Circuit Court case; Contract & Indebtedness | I28: 2020-000746-CA-01
A29: 2018-011311-CC-05 | B29: 2018-011311-CC-05 | C29: Entity | D29: ROA_SPINE | E29: YES | I29: 2018-011311-CC-05
A30: 3D25-1676 | B30: 3D25-1676 | C30: Appeal | D30: ROA_SPINE | E30: YES | F30: Third DCA Appeal | I30: 3D25-1676
A31: ELI_COHEN | B31: ELI COHEN | C31: Party | D31: ROA_SPINE | E31: YES | F31: Plaintiff / Appellant | I31: ELI_COHEN
A32: JEFF_ATLAS | B32: JEFF ATLAS | C32: Party | D32: ROA_SPINE | E32: YES | F32: Defendant / Appellee | I32: JEFF_ATLAS
A33: SUSAN_ATLAS | B33: SUSAN ATLAS | C33: Party | D33: ROA_SPINE | E33: YES | F33: Defendant / Appellee | I33: SUSAN_ATLAS
A34: HABER_LAW_LLP | B34: HABER LAW, LLP | C34: Law Firm | D34: ROA_SPINE | E34: YES | F34: Plaintiff's counsel | I34: HABER_LAW_LLP
A35: Ariella_J_Gutman | B35: Ariella J. Gutman | C35: Attorney | D35: ROA_SPINE | E35: YES | F35: Partner at Haber Law; Florida Bar No. 91447 | I35: Ariella_J_Gutman
A36: Simone_M_Honeygan | B36: Simone M. Honeygan | C36: Attorney | D36: ROA_SPINE | E36: YES | F36: Associate at Haber Law; Florida Bar No. 1026030 | I36: Simone_M_Honeygan
A37: David_B_Haber | B37: David B. Haber | C37: Attorney | D37: ROA_SPINE | E37: YES | F37: Senior Partner at Haber Law | I37: David_B_Haber
A38: Thomas_Butler | B38: Thomas Butler | C38: Attorney | D38: ROA_SPINE | E38: YES | F38: Former counsel for Defendants; Bar #569178 | I38: Thomas_Butler
A39: Judge_Reemberto_Diaz | B39: Judge Reemberto Diaz | C39: Judge | D39: ROA_SPINE | E39: YES | F39: Presiding judge CA30; entered SFJ | I39: Judge_Reemberto_Diaz
A40: Judge_Ruiz | B40: Judge Ruiz | C40: Judge | D40: ROA_SPINE | E40: YES | F40: Former presiding judge; disqualified 10/11/2024 | I40: Judge_Ruiz
A41: CIR-126 | B41: CIR-126 | C41: Entity | D41: ROA_SPINE | E41: YES | I41: CIR-126
A42: Judge_Del_Rio | B42: Judge Del Rio | C42: Judge | D42: ROA_SPINE | E42: YES | F42: Former presiding judge CA05; recused 01/17/2025 | I42: Judge_Del_Rio
A43: CIR-142 | B43: CIR-142 | C43: Entity | D43: ROA_SPINE | E43: YES | I43: CIR-142
A44: CIR-169/DIN169 | B44: CIR-169 / DIN 169 | C44: Judgment | D44: ROA_SPINE | E44: NO | F44: Summary Final Judgment | I44: DIN-169
A45: I-SUMMARY | B45: I-SUMMARY | C45: Entity | D45: ROA_SPINE | E45: YES | I45: I-SUMMARY
A46: CIR-99/DIN99 | B46: CIR-99 / DIN 99 | C46: Motion | D46: ROA_SPINE | E46: NO | F46: Defendants Motion for Summary Judgment (first) | I46: DIN-99
A47: CIR-109/DIN109 | B47: CIR-109 / DIN 109 | C47: Order | D47: ROA_SPINE | E47: NO | F47: Order Denying Defendants MSJ | I47: DIN-109
A48: CIR-135/DIN135 | B48: CIR-135 / DIN 135 | C48: Motion | D48: ROA_SPINE | E48: NO | F48: Amended Renewed MSJ + Sanctions | I48: DIN-135
A49: CIR-161/DIN161 | B49: CIR-161 / DIN 161 | C49: Order | D49: ROA_SPINE | E49: NO | F49: Order Denying Amended Renewed MSJ | I49: DIN-161
A50: CIR-164/DIN164 | B50: CIR-164 / DIN 164 | C50: Motion | D50: ROA_SPINE | E50: NO | F50: Plaintiff Motion for Summary Judgment | I50: DIN-164
A51: CIR-148/DIN148 | B51: CIR-148 / DIN 148 | C51: Reply | D51: ROA_SPINE | E51: NO | F51: Defendants Reply to Opposition | I51: DIN-148
A52: CIR-151/DIN151 | B52: CIR-151 / DIN 151 | C52: Motion | D52: ROA_SPINE | E52: NO | F52: Motion for Mandatory Transfer to County | I52: DIN-151
A53: CIR-158/DIN158 | B53: CIR-158 / DIN 158 | C53: Order | D53: ROA_SPINE | E53: NO | F53: Order Denying Mandatory Transfer | I53: DIN-158
A54: CIR-170/DIN170 | B54: CIR-170 / DIN 170 | C54: Notice | D54: ROA_SPINE | E54: NO | F54: Notice of Appeal | I54: DIN-170
A55: CIR-176/DIN176 | B55: CIR-176 / DIN 176 | C55: Order | D55: ROA_SPINE | E55: NO | F55: 3rd DCA Order - Transcripts Non-Compliant | I55: DIN-176
A56: CIR-178/DIN178 | B56: CIR-178 / DIN 178 | C56: Order | D56: ROA_SPINE | E56: NO | F56: 3rd DCA Order Denying Stay | I56: DIN-178
A57: E-SEC-01 | B57: E-SEC-01 | C57: Exhibit | D57: ROA_SPINE | E57: YES | F57: Notice of Intention to Impose Claim on Deposit | I57: E-SEC-01
A58: E-MOLD-01 | B58: E-MOLD-01 | C58: Exhibit | D58: ROA_SPINE | E58: YES | F58: Miami Mold Specialist Letter | I58: E-MOLD-01
A59: I-MAINT | B59: I-MAINT | C59: Entity | D59: ROA_SPINE | E59: YES | I59: I-MAINT
A60: E-WASH-01 | B60: E-WASH-01 | C60: Exhibit | D60: ROA_SPINE | E60: YES | F60: BrandsMart Washer/Dryer Receipt | I60: E-WASH-01
A61: E-CHW-01 | B61: E-CHW-01 | C61: Exhibit | D61: ROA_SPINE | E61: YES | F61: Choice Home Warranty Contract + Logs | I61: E-CHW-01
A62: I-MISREP | B62: I-MISREP | C62: Entity | D62: ROA_SPINE | E62: YES | I62: I-MISREP
A63: E-LEASE-01 | B63: E-LEASE-01 | C63: Exhibit | D63: ROA_SPINE | E63: YES | F63: Lease Agreement TH-A5 | I63: E-LEASE-01
A64: E-MURANO-01 | B64: E-MURANO-01 | C64: Exhibit | D64: ROA_SPINE | E64: YES | F64: Murano Rules & Regulations | I64: E-MURANO-01
A65: Police_Report_2019-00042552 | B65: Police Report #2019-00042552 | C65: Exhibit | D65: ROA_SPINE | E65: YES | F65: Referenced in Defendants Reply; spoliation evidence | I65: Police_Report_2019-00042552
A66: Hearing_05_23_2024 | B66: Hearing 05/23/2024 | C66: Hearing | D66: ROA_SPINE | E66: YES | F66: Defendants MSJ hearing | I66: Hearing_05_23_2024
A67: Hearing_03_13_2025 | B67: Hearing 03/13/2025 | C67: Hearing | D67: ROA_SPINE | E67: YES | F67: Transfer Motion hearing | I67: Hearing_03_13_2025
A68: Hearing_07_21_2025 | B68: Hearing 07/21/2025 | C68: Hearing | D68: ROA_SPINE | E68: YES | F68: Special Set - SFJ hearing | I68: Hearing_07_21_2025
A69: Mediation_11_01_2021 | B69: Mediation 11/01/2021 | C69: ADR | D69: ROA_SPINE | E69: YES | F69: Mediation conference; no agreement | I69: Mediation_11_01_2021
A70: 05_18_2018 | B70: 05/18/2018 | C70: Date | D70: ROA_SPINE | E70: YES | F70: Original County filing | I70: 05_18_2018
A71: 12_22_2017 | B71: 12/22/2017 | C71: Date | D71: ROA_SPINE | E71: YES | F71: Lease execution | I71: 12_22_2017
A72: 01_06_2018 | B72: 01/06/2018 | C72: Date | D72: ROA_SPINE | E72: YES | F72: Security deposit notice | I72: 01_06_2018
A73: 01_14_2020 | B73: 01/14/2020 | C73: Date | D73: ROA_SPINE | E73: YES | F73: Circuit filing after transfer | I73: 01_14_2020
A74: 08_02_2025 | B74: 08/02/2025 | C74: Date | D74: ROA_SPINE | E74: YES | F74: Summary Final Judgment entered | I74: 08_02_2025
... A76: 1272649 | B76: $12,726.49 | C76: Amount | D76: ROA_SPINE | E76: YES | F76: Plaintiff's judicial admission of damages | I76: 1272649
A77: I-JURIS | B77: I-JURIS | C77: Entity | D77: ROA_SPINE | E77: YES | I77: I-JURIS
A78: 15000 | B78: $15,000 | C78: Threshold | D78: ROA_SPINE | E78: YES | F78: County Court jurisdictional limit | I78: 15000
A79: 12562763 | B79: $125,627.63 | C79: Amount | D79: ROA_SPINE | E79: YES | F79: Fee request post-SFJ | I79: 12562763
A80: CIR-173/DIN173 | B80: CIR-173 / DIN 173 | C80: Entity | D80: ROA_SPINE | E80: NO | I80: DIN-173
A81: REPLY-A1 | B81: REPLY-A1 | C81: Motion_Assertion | D81: MOTION_ASSERTION | E81: YES | F81: Defendants argue Plaintiff fails Rule 1.510 burden | I81: REPLY-A1
A82: Fla_R_Civ_P_1510 | B82: Fla. R. Civ. P. 1.510 | C82: Entity | D82: MOTION_ASSERTION | E82: YES | I82: Fla_R_Civ_P_1510
A83: REPLY-A2 | B83: REPLY-A2 | C83: Motion_Assertion | D83: MOTION_ASSERTION | E83: YES | F83: Defendants argue Plaintiff relies on improper support | I83: REPLY-A2
A84: REPLY-A3 | B84: REPLY-A3 | C84: Motion_Assertion | D84: MOTION_ASSERTION | E84: YES | F84: Defendants argue renewed MSJ permitted under Florida law | I84: REPLY-A3
A85: REPLY-A4 | B85: REPLY-A4 | C85: Motion_Assertion | D85: MOTION_ASSERTION | E85: YES | F85: Defendants argue prior rulings voidable after recusal | I85: REPLY-A4
A86: Fla_R_Jud_Admin_2330h | B86: Fla. R. Jud. Admin. 2.330(h) | C86: Entity | D86: MOTION_ASSERTION | E86: YES | I86: Fla_R_Jud_Admin_2330h
A87: REPLY-A5 | B87: REPLY-A5 | C87: Motion_Assertion | D87: MOTION_ASSERTION | E87: YES | F87: Defendants argue spoliation occurred | I87: REPLY-A5
A88: REPLY-A6 | B88: REPLY-A6 | C88: Motion_Assertion | D88: MOTION_ASSERTION | E88: YES | F88: Defendants argue washer/dryer could have been repaired | I88: REPLY-A6
A89: REPLY-A7 | B89: REPLY-A7 | C89: Motion_Assertion | D89: MOTION_ASSERTION | E89: YES | F89: Defendants invoke Valcin adverse inference | I89: REPLY-A7
A90: Public_Health_Trust_v_Valcin | B90: Public Health Trust v. Valcin | C90: Entity | D90: MOTION_ASSERTION | E90: YES | I90: Public_Health_Trust_v_Valcin
A91: REPLY-A8 | B91: REPLY-A8 | C91: Motion_Assertion | D91: MOTION_ASSERTION | E91: YES | F91: Defendants argue damages unverified | I91: REPLY-A8
A92: REPLY-A9 | B92: REPLY-A9 | C92: Motion_Assertion | D92: MOTION_ASSERTION | E92: YES | F92: Defendants cite Miami Mold subpoenaed records | I92: REPLY-A9
A93: REPLY-A10 | B93: REPLY-A10 | C93: Motion_Assertion | D93: MOTION_ASSERTION | E93: YES | F93: Defendants argue no causation established | I93: REPLY-A10
A94: REPLY-A11 | B94: REPLY-A11 | C94: Motion_Assertion | D94: MOTION_ASSERTION | E94: YES | F94: Defendants argue lack of notice bars recovery | I94: REPLY-A11
A95: REPLY-A12 | B95: REPLY-A12 | C95: Motion_Assertion | D95: MOTION_ASSERTION | E95: YES | F95: Defendants seek summary judgment as matter of law | I95: REPLY-A12
A96: Def_Motion_Ex_11_Miami_Mold | B96: Def. Motion Ex. 11 (Miami Mold) | C96: Evidence_Reference | D96: MOTION_ASSERTION | E96: YES | F96: Subpoenaed contemporaneous records | I96: Def_Motion_Ex_11_Miami_Mold
A97: Manufacturer_Warranty | B97: Manufacturer Warranty | C97: Evidence_Reference | D97: MOTION_ASSERTION | E97: YES | F97: Warranty on washer/dryer | I97: Manufacturer_Warranty
A98: Public_Health_Trust_v_Valcin_507_So_2d_596_Fla_1987 | B98: Public Health Trust v. Valcin, 507 So. 2d 596 (Fla. 1987) | C98: Case | D98: MOTION_ASSERTION | E98: YES | F98: Spoliation adverse inference doctrine | I98: Public_Health_Trust_v_Valcin_507_So_2d_596_Fla_1987
A99: FOF-1 | B99: FOF-1 | C99: Court_Finding | D99: COURT_FINDING | E99: YES | F99: Lease executed; term 12/22/2017 to 12/21/2018 | I99: FOF-1
A100: FOF-2 | B100: FOF-2 | C100: Court_Finding | D100: COURT_FINDING | E100: YES | F100: Lease allocates tenant responsibility to 3 items only | I100: FOF-2
A101: FOF-3 | B101: FOF-3 | C101: Court_Finding | D101: COURT_FINDING | E101: YES | F101: All other maintenance = Defendants' responsibility | I101: FOF-3
...

Sheet EDGES
A1: Edge_ID | B1: From_Entity_ID | C1: To_Entity_ID | D1: Relation_Type | E1: Layer | F1: Evidence_RecordItem_IDs | G1: Evidence_Authority_IDs | H1: Evidence_Quote_Verbatim | I1: Quote_WC | J1: Quote_Verified | K1: Notes | L1: Confidence | M1: Evidence_Summary | N1: Quote_Compliant
A2: E00001 | B2: DOC-ROA-TXT | C2: ROA-TXT-5960 | D2: CONTAINS | E2: ROA_SPINE | F2: ROA-TXT-5960 | H2: NOTICE OF INTENTION TO IMPOSE CLAIM ON SECURITY DEPOSIT | I2: 9 | J2: UNREVIEWED | L2: High | N2: YES
A3: E00002 | B3: DOC-ROA-TXT | C3: ROA-TXT-5962 | D3: CONTAINS | E3: ROA_SPINE | F3: ROA-TXT-5962 | I3: 4 | J3: UNREVIEWED | L3: High | M3: DATE: January 6th, 2018 | N3: NO
A4: E00003 | B4: DOC-ROA-TXT | C4: ROA-TXT-1336 | D4: CONTAINS | E4: ROA_SPINE | F4: ROA-TXT-1336 | I4: 1 | J4: UNREVIEWED | L4: High | M4: ESTIMATE | N4: NO
A5: E00004 | B5: DOC-ROA-TXT | C5: ROA-TXT-17966 | D5: CONTAINS | E5: ROA_SPINE | F5: ROA-TXT-17966 | I5: 24 | J5: UNREVIEWED | L5: High | M5: pt for Payment Amount: $6,500,00 | f nns;ic1ion rmte: 01i2'1!201 a Mc1hod oi payncnt: Ca.sh | Payricnl ol Invoice #80623 | N5: NO
A6: E00005 | B6: DOC-ROA-TXT | C6: ROA-TXT-16626 | D6: CONTAINS | E6: ROA_SPINE | F6: ROA-TXT-16626 | I6: 45 | J6: UNREVIEWED | L6: High | M6: ~o proof of payment exists of the S6.500.UO cash paymentthat Eli Cohen made tu Miami \fold LLC for mold remediation pcrfoHrn:d at his apartmc:nt located at: 1000 South Pointe Drive. Unit TI-f-/\5, Miami Beach, Fl, 33139 other than invoice # | N6: NO
A7: E00006 | B7: DOC-ROA-TXT | C7: ROA-TXT-18011 | D7: CONTAINS | E7: ROA_SPINE | F7: ROA-TXT-18011 | H7: Police Report #2019-00042552 documents Plaintiff's unauthorized removal and disposal of Defendant's property .. | I7: 15 | J7: UNREVIEWED | L7: High | N7: YES
A8: E00007 | B8: DOC-ROA-TXT | C8: ROA-TXT-18017 | D8: CONTAINS | E8: ROA_SPINE | F8: ROA-TXT-18017 | H8: Under Public Health Trust v. Valcin, 507 So. 2d 596 (Fla. 1987), this mandates an adverse inference. | I8: 17 | J8: UNREVIEWED | L8: High | N8: YES
A9: E00008 | B9: ROA-TXT-5960 | C9: I-SECDEP | D9: SUPPORTS_ISSUE | E9: EVIDENCE_ITEM | F9: ROA-TXT-5960 | H9: NOTICE OF INTENTION TO IMPOSE CLAIM ON SECURITY DEPOSIT | I9: 9 | J9: UNREVIEWED | L9: Medium | N9: YES
A10: E00009 | B10: ROA-TXT-5962 | C10: I-SECDEP | D10: SUPPORTS_ISSUE | E10: EVIDENCE_ITEM | F10: ROA-TXT-5962 | I10: 4 | J10: UNREVIEWED | L10: Medium | M10: DATE: January 6th, 2018 | N10: NO
A11: E00010 | B11: ROA-TXT-1336 | C11: I-DAMAGES | D11: SUPPORTS_ISSUE | E11: EVIDENCE_ITEM | F11: ROA-TXT-1336 | I11: 1 | J11: UNREVIEWED | L11: Medium | M11: ESTIMATE | N11: NO
A12: E00011 | B12: ROA-TXT-17966 | C12: I-DAMAGES | D12: SUPPORTS_ISSUE | E12: EVIDENCE_ITEM | F12: ROA-TXT-17966 | I12: 24 | J12: UNREVIEWED | L12: Medium | M12: pt for Payment Amount: $6,500,00 | f nns;ic1ion rmte: 01i2'1!201 a Mc1hod oi payncnt: Ca.sh | Payricnl ol Invoice #80623 | N12: NO
A13: E00012 | B13: ROA-TXT-16626 | C13: I-DAMAGES | D13: SUPPORTS_ISSUE | E13: EVIDENCE_ITEM | F13: ROA-TXT-16626 | I13: 45 | J13: UNREVIEWED | L13: Medium | M13: ~o proof of payment exists of the S6.500.UO cash paymentthat Eli Cohen made tu Miami \fold LLC for mold remediation pcrfoHrn:d at his apartmc:nt located at: 1000 South Pointe Drive. Unit TI-f-/\5, Miami Beach, Fl, 33139 other than invoice # | N13: NO
A14: E00013 | B14: ROA-TXT-18011 | C14: I-SPOLIATION | D14: SUPPORTS_ISSUE | E14: MOTION_ASSERTION | F14: ROA-TXT-18011 | H14: Police Report #2019-00042552 documents Plaintiff's unauthorized removal and disposal of Defendant's property .. | I14: 15 | J14: UNREVIEWED | L14: Medium | N14: YES
A15: E00014 | B15: ROA-TXT-18017 | C15: I-SPOLIATION | D15: SUPPORTS_ISSUE | E15: MOTION_ASSERTION | F15: ROA-TXT-18017 | H15: Under Public Health Trust v. Valcin, 507 So. 2d 596 (Fla. 1987), this mandates an adverse inference. | I15: 17 | J15: UNREVIEWED | L15: Medium | N15: YES
A16: E00015 | B16: AUTH-FL-VALCIN | C16: I-SPOLIATION | D16: SUPPORTS_ISSUE | E16: EVIDENCE_ITEM | G16: AUTH-FL-VALCIN | I16: 1 | J16: UNREVIEWED | L16: Medium | M16: [PROPOSITION_PENDING] | N16: NO
A17: E00016 | B17: AUTH-FL-RULE-1510 | C17: I-DAMAGES | D17: SUPPORTS_ISSUE | E17: EVIDENCE_ITEM | G17: AUTH-FL-RULE-1510 | H17: SJ requires no genuine dispute of material fact. | I17: 8 | J17: UNREVIEWED | L17: Medium | N17: YES
A18: E00017 | B18: CLM-DAM-001 | C18: I-DAMAGES | D18: BELONGS_TO | E18: EVIDENCE_ITEM | I18: 0 | J18: UNREVIEWED | K18: T1 | L18: High | N18: NO
A19: E00018 | B19: CLM-DAM-001 | C19: ROA-TXT-1336 | D19: EVIDENCED_BY | E19: EVIDENCE_ITEM | F19: ROA-TXT-1336 | I19: 1 | J19: UNREVIEWED | L19: Medium | M19: ESTIMATE | N19: NO
A20: E00019 | B20: CLM-DAM-002 | C20: I-DAMAGES | D20: BELONGS_TO | E20: EVIDENCE_ITEM | I20: 0 | J20: UNREVIEWED | K20: T1 | L20: High | N20: NO
A21: E00020 | B21: CLM-DAM-002 | C21: ROA-TXT-16626 | D21: EVIDENCED_BY | E21: EVIDENCE_ITEM | F21: ROA-TXT-16626 | I21: 45 | J21: UNREVIEWED | L21: Medium | M21: ~o proof of payment exists of the S6.500.UO cash paymentthat Eli Cohen made tu Miami \fold LLC for mold remediation pcrfoHrn:d at his apartmc:nt located at: 1000 South Pointe Drive. Unit TI-f-/\5, Miami Beach, Fl, 33139 other than invoice # | N21: NO
A22: E00021 | B22: CLM-DAM-002 | C22: ROA-TXT-17966 | D22: EVIDENCED_BY | E22: EVIDENCE_ITEM | F22: ROA-TXT-17966 | I22: 24 | J22: UNREVIEWED | L22: Medium | M22: pt for Payment Amount: $6,500,00 | f nns;ic1ion rmte: 01i2'1!201 a Mc1hod oi payncnt: Ca.sh | Payricnl ol Invoice #80623 | N22: NO
A23: E00022 | B23: CLM-SPO-001 | C23: I-SPOLIATION | D23: BELONGS_TO | E23: EVIDENCE_ITEM | I23: 0 | J23: UNREVIEWED | K23: T1 (motion assertion) | L23: High | N23: NO
A24: E00023 | B24: CLM-SPO-001 | C24: ROA-TXT-18011 | D24: EVIDENCED_BY | E24: MOTION_ASSERTION | F24: ROA-TXT-18011 | H24: Police Report #2019-00042552 documents Plaintiff's unauthorized removal and disposal of Defendant's property .. | I24: 15 | J24: UNREVIEWED | L24: Medium | N24: YES
A25: E00024 | B25: CLM-SPO-002 | C25: I-SPOLIATION | D25: BELONGS_TO | E25: EVIDENCE_ITEM | I25: 0 | J25: UNREVIEWED | K25: T2 | L25: High | N25: NO
A26: E00025 | B26: CLM-SPO-002 | C26: ROA-TXT-18017 | D26: EVIDENCED_BY | E26: MOTION_ASSERTION | F26: ROA-TXT-18017 | H26: Under Public Health Trust v. Valcin, 507 So. 2d 596 (Fla. 1987), this mandates an adverse inference. | I26: 17 | J26: UNREVIEWED | L26: Medium | N26: YES
A27: E00026 | B27: CLM-SPO-002 | C27: AUTH-FL-VALCIN | D27: SUPPORTED_BY | E27: EVIDENCE_ITEM | G27: AUTH-FL-VALCIN | I27: 1 | J27: UNREVIEWED | L27: Medium | M27: [PROPOSITION_PENDING] | N27: NO
A28: E00027 | B28: CON-001 | C28: I-DAMAGES | D28: AFFECTS | E28: EVIDENCE_ITEM | I28: 0 | J28: UNREVIEWED | L28: High | N28: NO
A29: E00028 | B29: CON-001 | C29: ROA-TXT-16626 | D29: INVOLVES | E29: EVIDENCE_ITEM | F29: ROA-TXT-16626 | I29: 45 | J29: UNREVIEWED | L29: High | M29: ~o proof of payment exists of the S6.500.UO cash paymentthat Eli Cohen made tu Miami \fold LLC for mold remediation pcrfoHrn:d at his apartmc:nt located at: 1000 South Pointe Drive. Unit TI-f-/\5, Miami Beach, Fl, 33139 other than invoice # | N29: NO
A30: E00029 | B30: CON-001 | C30: ROA-TXT-17966 | D30: INVOLVES | E30: EVIDENCE_ITEM | F30: ROA-TXT-17966 | I30: 24 | J30: UNREVIEWED | L30: High | M30: pt for Payment Amount: $6,500,00 | f nns;ic1ion rmte: 01i2'1!201 a Mc1hod oi payncnt: Ca.sh | Payricnl ol Invoice #80623 | N30: NO
A31: E00030 | B31: HT-VALCIN-PROP | C31: I-SPOLIATION | D31: BLOCKS | E31: ROA_SPINE | I31: 0 | J31: UNREVIEWED | K31: Populate Valcin proposition text from approved source (no web unless allowed). | L31: High | N31: NO
A32: E00031 | B32: HT-POLICE-REPORT | C32: I-SPOLIATION | D32: BLOCKS | E32: ROA_SPINE | I32: 0 | J32: UNREVIEWED | K32: Ingest Police Report #2019-00042552 into RecordItems with quote-ready excerpt. | L32: High | N32: NO
A33: E00032 | B33: HT-DRIMMER-PDF | C33: I-DAMAGES | D33: BLOCKS | E33: ROA_SPINE | I33: 0 | J33: UNREVIEWED | K33: Extract clean Drimmer exhibit quote (ESTIMATE/DELIVERY ONLY) from ROA PDF for use in brief. | L33: High | N33: NO
A34: E00033 | B34: 2020-000746-CA-01 | C34: 2018-011311-CC-05 | D34: TRANSFERRED_FROM | E34: ROA_SPINE | H34: Related Cases Case Number: 2018-011311-CC-05 Filing Date: 05/18/2018 | I34: 13 | J34: UNREVIEWED | K34: Imported from JSON | L34: Medium | N34: YES
A35: E00034 | B35: 2018-011311-CC-05 | C35: 2020-000746-CA-01 | D35: TRANSFERRED_TO | E35: ROA_SPINE | H35: Case Type: Contract and Indebtedness ($8,001- $15,000) | I35: 9 | J35: UNREVIEWED | K35: Imported from JSON | L35: Medium | N35: YES
A36: E00035 | B36: 3D25-1676 | C36: 2020-000746-CA-01 | D36: APPEAL_OF | E36: ROA_SPINE | H36: Notice of Appeal Event [DIN 170, 09/02/2025] | I36: 9 | J36: UNREVIEWED | K36: Imported from JSON | L36: Medium | N36: YES
A37: E00036 | B37: ELI_COHEN | C37: 2020-000746-CA-01 | D37: PLAINTIFF_IN | E37: ROA_SPINE | H37: Case Style: ELI COHEN vs JEFF ATLAS et al | I37: 9 | J37: UNREVIEWED | K37: Imported from JSON | L37: Medium | N37: YES
A38: E00037 | B38: JEFF_ATLAS | C38: 2020-000746-CA-01 | D38: DEFENDANT_IN | E38: ROA_SPINE | I38: 3 | J38: UNREVIEWED | K38: Imported from JSON | L38: Medium | M38: Defendant ATLAS, JEFF | N38: NO
A39: E00038 | B39: SUSAN_ATLAS | C39: 2020-000746-CA-01 | D39: DEFENDANT_IN | E39: ROA_SPINE | I39: 3 | J39: UNREVIEWED | K39: Imported from JSON | L39: Medium | M39: Defendant ATLAS, SUSAN | N39: NO
A40: E00039 | B40: HABER_LAW_LLP | C40: ELI_COHEN | D40: REPRESENTS | E40: ROA_SPINE | H40: HABER LAW, LLP 251 NW 23rd Street Miami, Florida 33127 | I40: 10 | J40: UNREVIEWED | K40: Imported from JSON | L40: Medium | N40: YES
A41: E00040 | B41: Ariella_J_Gutman | C41: ELI_COHEN | D41: COUNSEL_FOR | E41: ROA_SPINE | H41: ARIELLA J. GUTMAN, ESQ. Fla Bar No. 91447 agutman@haber.law | I41: 11 | J41: UNREVIEWED | K41: Imported from JSON | L41: Medium | N41: YES
A42: E00041 | B42: Simone_M_Honeygan | C42: ELI_COHEN | D42: COUNSEL_FOR | E42: ROA_SPINE | H42: SIMONE M. HONEYGAN, ESQ. Florida Bar No. 1026030 shoneygan@haber.law | I42: 11 | J42: UNREVIEWED | K42: Imported from JSON | L42: Medium | N42: YES
A43: E00042 | B43: David_B_Haber | C43: HABER_LAW_LLP | D43: PARTNER_AT | E43: ROA_SPINE | I43: 6 | J43: UNREVIEWED | K43: Imported from JSON | L43: Medium | M43: David Brian Haber: dhaber@haber.law | N43: NO
A44: E00043 | B44: Thomas_Butler | C44: JEFF_ATLAS | D44: FORMER_COUNSEL_FOR | E44: ROA_SPINE | I44: 7 | J44: UNREVIEWED | K44: Imported from JSON | L44: Medium | M44: Defendant ATLAS, JEFF B#: 569178 Thomas Butler | N44: NO
A45: E00044 | B45: Judge_Reemberto_Diaz | C45: 2020-000746-CA-01 | D45: PRESIDES_OVER | E45: ROA_SPINE | I45: 7 | J45: UNREVIEWED | K45: Imported from JSON | L45: Medium | M45: Judicial Section: CA30 - Downtown Miami - JudgeDiaz, Reemberto | N45: NO
A46: E00045 | B46: Judge_Ruiz | C46: CIR-126 | D46: DISQUALIFIED_BY | E46: ROA_SPINE | H46: Order Granting Disqualification (Ruiz) [DIN 126, 10/11/2024] | I46: 9 | J46: UNREVIEWED | K46: Imported from JSON | L46: Medium | N46: YES
A47: E00046 | B47: Judge_Del_Rio | C47: CIR-142 | D47: RECUSED_VIA | E47: ROA_SPINE | H47: Order of Recusal (Del Rio) [DIN 142, 01/17/2025] - Del Rio recused; to CA30 Diaz | I47: 16 | J47: UNREVIEWED | K47: Imported from JSON | L47: Medium | N47: YES
A48: E00047 | B48: DIN-169 | C48: Judge_Reemberto_Diaz | D48: ENTERED_BY | E48: ROA_SPINE | H48: Summary Final Judgment [DIN 169, 08/02/2025] Record_Pages: 1341-1354 | I48: 11 | J48: UNREVIEWED | K48: Imported from JSON | L48: Medium | N48: YES
A49: E00048 | B49: DIN-169 | C49: I-SUMMARY | D49: TAGGED_ISSUE | E49: ROA_SPINE | H49: Grants SJ all counts; awards fees under Lease + §83.48 | I49: 10 | J49: UNREVIEWED | K49: Imported from JSON | L49: Medium | N49: YES
A50: E00049 | B50: DIN-99 | C50: JEFF_ATLAS | D50: FILED_BY | E50: ROA_SPINE | H50: Defendants Motion for Summary Judgment [DIN 99, 03/08/2024] Record_Pages: 326-339 | I50: 13 | J50: UNREVIEWED | K50: Imported from JSON | L50: Medium | N50: YES
A51: E00050 | B51: DIN-109 | C51: Judge_Ruiz | D51: ENTERED_BY | E51: ROA_SPINE | H51: Order Denying Defendants MSJ [DIN 109, 06/05/2024] - No evidence presented; factual dispute | I51: 14 | J51: UNREVIEWED | K51: Imported from JSON | L51: Medium | N51: YES
A52: E00051 | B52: DIN-135 | C52: JEFF_ATLAS | D52: FILED_BY | E52: ROA_SPINE | H52: Amended Renewed MSJ + Sanctions [DIN 135, 12/22/2024] Record_Pages: 714-840 (127 pages) | I52: 14 | J52: UNREVIEWED | K52: Imported from JSON | L52: Medium | N52: YES
A53: E00052 | B53: DIN-161 | C53: Judge_Reemberto_Diaz | D53: ENTERED_BY | E53: ROA_SPINE | H53: Order Denying Amended Renewed MSJ [DIN 161, 04/01/2025] - Treats as reconsideration; reasons on record | I53: 16 | J53: UNREVIEWED | K53: Imported from JSON | L53: Medium | N53: YES
A54: E00053 | B54: DIN-164 | C54: ELI_COHEN | D54: FILED_BY | E54: ROA_SPINE | H54: Plaintiff Motion for Summary Judgment [DIN 164, 05/01/2025] Record_Pages: 1137-1301 (165 pages) | I54: 15 | J54: UNREVIEWED | K54: Imported from JSON | L54: Medium | N54: YES
A55: E00054 | B55: DIN-148 | C55: JEFF_ATLAS | D55: FILED_BY | E55: ROA_SPINE | H55: Defendants Reply to Opposition [DIN 148, 02/10/2025] Record_Pages: 1036-1039 | I55: 12 | J55: UNREVIEWED | K55: Imported from JSON | L55: Medium | N55: YES
A56: E00055 | B56: DIN-151 | C56: JEFF_ATLAS | D56: FILED_BY | E56: ROA_SPINE | H56: Motion for Mandatory Transfer to County [DIN 151, 03/01/2025] - $12,726.49 judicial admission | I56: 16 | J56: UNREVIEWED | K56: Imported from JSON | L56: Medium | N56: YES
A57: E00056 | B57: DIN-158 | C57: Judge_Reemberto_Diaz | D57: ENTERED_BY | E57: ROA_SPINE | H57: Order Denying Mandatory Transfer [DIN 158, 03/19/2025] - DENIED for reasons on record | I57: 14 | J57: UNREVIEWED | K57: Imported from JSON | L57: Medium | N57: YES
... A62: E00061 | B62: E-MOLD-01 | C62: I-MAINT | D62: SUPPORTS_ISSUE | E62: ROA_SPINE | H62: No proof of $6,500 payment [dated 06/03/2019] | I62: 10 | J62: UNREVIEWED | K62: Imported from JSON | L62: Medium | N62: YES
A63: E00062 | B63: E-WASH-01 | C63: I-MAINT | D63: SUPPORTS_ISSUE | E63: ROA_SPINE | I63: 6 | J63: UNREVIEWED | K63: Imported from JSON | L63: Medium | M63: Atlas purchased before lease [dated 2017] | N63: NO
A64: E00063 | B64: E-CHW-01 | C64: I-MISREP | D64: SUPPORTS_ISSUE | E64: ROA_SPINE | I64: 7 | J64: UNREVIEWED | K64: Imported from JSON | L64: Medium | M64: Denials for pre-existing conditions [2018-2019] | N64: NO
A65: E00064 | B65: E-LEASE-01 | C65: 2020-000746-CA-01 | D65: GOVERNS | E65: ROA_SPINE | H65: §VII duties; §XXIII fees; §83.49 [dated 12/22/2017] | I65: 10 | J65: UNREVIEWED | K65: Imported from JSON | L65: Medium | N65: YES
A66: E00065 | B66: E-MURANO-01 | C66: I-MAINT | D66: SUPPORTS_ISSUE | E66: ROA_SPINE | H66: 24-hour mold notice; no self-remediation [dated 02/2018] | I66: 10 | J66: UNREVIEWED | K66: Imported from JSON | L66: Medium | N66: YES
A67: E00066 | B67: Police_Report_2019-00042552 | C67: I-SPOLIATION | D67: SUPPORTS_ISSUE | E67: ROA_SPINE | H67: Police Report #2019-00042552 documents Plaintiff's unauthorized removal and disposal of Defendant's property | I67: 15 | J67: UNREVIEWED | K67: Imported from JSON | L67: Medium | N67: YES
A68: E00067 | B68: Hearing_05_23_2024 | C68: DIN-99 | D68: HEARING_ON | E68: ROA_SPINE | H68: Notice of Hrg Special Appt Event 05-23-2024 at 11:00 AM [DIN 102] | I68: 15 | J68: UNREVIEWED | K68: Imported from JSON | L68: Medium | N68: YES
A69: E00068 | B69: Hearing_03_13_2025 | C69: DIN-151 | D69: HEARING_ON | E69: ROA_SPINE | H69: Motion Calendar Hearing DEFENDANTS' MOTION FOR MANDATORY TRANSFER TO COUNTY COURT [03/13/2025] | I69: 14 | J69: UNREVIEWED | K69: Imported from JSON | L69: Medium | N69: YES
A70: E00069 | B70: Hearing_07_21_2025 | C70: DIN-164 | D70: HEARING_ON | E70: ROA_SPINE | H70: Special Sets Hearing [07/21/2025 at 09:30 AM] | I70: 10 | J70: UNREVIEWED | K70: Imported from JSON | L70: Medium | N70: YES
A71: E00070 | B71: Mediation_11_01_2021 | C71: 2020-000746-CA-01 | D71: ADR_IN | E71: ROA_SPINE | H71: The parties mediated the issues in dispute on November 1, 2021. Unfortunately, no agreement was reached at mediation. | I71: 18 | J71: UNREVIEWED | K71: Imported from JSON | L71: Medium | N71: YES
A72: E00071 | B72: 05_18_2018 | C72: 2018-011311-CC-05 | D72: FILED_ON | E72: ROA_SPINE | I72: 5 | J72: UNREVIEWED | K72: Imported from JSON | L72: Medium | M72: Filing Date: 05/18/2018 | N72: NO
A73: E00072 | B73: 12_22_2017 | C73: E-LEASE-01 | D73: EXECUTED_ON | E73: ROA_SPINE | H73: Lease Agreement TH-A5 [dated 12/22/2017] | I73: 8 | J73: UNREVIEWED | K73: Imported from JSON | L73: Medium | N73: YES
A74: E00073 | B74: 01_06_2018 | C74: E-SEC-01 | D74: DATED | E74: ROA_SPINE | H74: Notice of Intention to Impose Claim on Deposit [01/06/2018] | I74: 11 | J74: UNREVIEWED | K74: Imported from JSON | L74: Medium | N74: YES
A75: E00074 | B75: 01_14_2020 | C75: 2020-000746-CA-01 | D75: FILED_ON | E75: ROA_SPINE | I75: 5 | J75: UNREVIEWED | K75: Imported from JSON | L75: Medium | M75: Filing Date: 01/14/2020 | N75: NO
A76: E00075 | B76: 08_02_2025 | C76: DIN-169 | D76: ENTERED_ON | E76: ROA_SPINE | H76: Summary Final Judgment [DIN 169, 08/02/2025] | I76: 8 | J76: UNREVIEWED | K76: Imported from JSON | L76: Medium | N76: YES
A77: E00076 | B77: 09_02_2025 | C77: DIN-170 | D77: FILED_ON | E77: ROA_SPINE | H77: Notice of Appeal [DIN 170, 09/02/2025] | I77: 8 | J77: UNREVIEWED | K77: Imported from JSON | L77: Medium | N77: YES
A78: E00077 | B78: 1272649 | C78: I-JURIS | D78: AMOUNT_IN_CONTROVERSY | E78: ROA_SPINE | H78: Motion for Mandatory Transfer to County [DIN 151] - $12,726.49 judicial admission | I78: 13 | J78: UNREVIEWED | K78: Imported from JSON | L78: Medium | N78: YES
A79: E00078 | B79: 15000 | C79: I-JURIS | D79: JURISDICTIONAL_LIMIT | E79: ROA_SPINE | H79: Case Type: Contract and Indebtedness ($8,001- $15,000) | I79: 9 | J79: UNREVIEWED | K79: Imported from JSON | L79: Medium | N79: YES
A80: E00079 | B80: 12562763 | C80: DIN-173 | D80: FEE_AMOUNT | E80: ROA_SPINE | H80: Motion for Attorney Fees [DIN 173] - $125,627.63 fee request; 9.87:1 ratio | I80: 15 | J80: UNREVIEWED | K80: Imported from JSON | L80: Medium | N80: YES
A81: E00080 | B81: REPLY-A1 | C81: Fla_R_Civ_P_1510 | D81: CITES_RULE | E81: MOTION_ASSERTION | I81: 29 | J81: UNREVIEWED | K81: Imported from JSON | L81: Medium | M81: Plaintiff fails to meet their burden under Fla. R. Civ. P. 1.510. The revised federal-aligned standard requires specific, admissible evidence demonstrating a genuine dispute of material fact. | N81: NO
A82: E00081 | B82: REPLY-A2 | C82: ELI_COHEN | D82: ACCUSES | E82: MOTION_ASSERTION | H82: Misrepresentations of the law and baseless, conclusory statements without any cited support. | I82: 12 | J82: UNREVIEWED | K82: Imported from JSON | L82: Medium | N82: YES
A83: E00082 | B83: REPLY-A3 | C83: DIN-135 | D83: JUSTIFIES | E83: MOTION_ASSERTION | H83: Florida law permits renewed summary judgment motions when new legal arguments or evidence are raised. | I83: 15 | J83: UNREVIEWED | K83: Imported from JSON | L83: Medium | N83: YES
A84: E00083 | B84: REPLY-A4 | C84: Fla_R_Jud_Admin_2330h | D84: CITES_RULE | E84: MOTION_ASSERTION | H84: Fla. R. Jud. Admin. 2.330(h) requires reconsideration of all rulings by a recused judge. | I84: 16 | J84: UNREVIEWED | K84: Imported from JSON | L84: Medium | N84: YES
A85: E00084 | B85: REPLY-A5 | C85: Police_Report_2019-00042552 | D85: EVIDENCED_BY | E85: MOTION_ASSERTION | H85: Police Report #2019-00042552 documents Plaintiff's unauthorized removal and disposal of Defendant's property. | I85: 15 | J85: UNREVIEWED | K85: Imported from JSON | L85: Medium | N85: YES
A86: E00085 | B86: REPLY-A6 | C86: E-WASH-01 | D86: RELATES_TO | E86: MOTION_ASSERTION | H86: The washer/dryer was under manufacturer warranty—it could have been repaired rather than destroyed. | I86: 15 | J86: UNREVIEWED | K86: Imported from JSON | L86: Medium | N86: YES
A87: E00086 | B87: REPLY-A7 | C87: Public_Health_Trust_v_Valcin | D87: CITES_AUTHORITY | E87: MOTION_ASSERTION | H87: Under Public Health Trust v. Valcin, 507 So. 2d 596 (Fla. 1987), this mandates an adverse inference. | I87: 17 | J87: UNREVIEWED | K87: Imported from JSON | L87: Medium | N87: YES
A88: E00087 | B88: REPLY-A8 | C88: I-DAMAGES | D88: ATTACKS | E88: MOTION_ASSERTION | I88: 27 | J88: UNREVIEWED | K88: Imported from JSON | L88: Medium | M88: Plaintiff's allegations rely on nothing more than unpaid estimates for a washer dryer and unsupported invoices for the alleged remediation, offering no proof of actual payment. | N88: NO
A89: E00088 | B89: REPLY-A9 | C89: E-MOLD-01 | D89: EVIDENCED_BY | E89: MOTION_ASSERTION | H89: Miami Mold's subpoenaed contemporaneous records (Def. Motion Ex. 11), which confirms 'no proof of payment exists.' | I89: 17 | J89: UNREVIEWED | K89: Imported from JSON | L89: Medium | N89: YES
A90: E00089 | B90: REPLY-A10 | C90: I-DAMAGES | D90: ATTACKS | E90: MOTION_ASSERTION | H90: Plaintiff fails to establish causation, offering no admissible evidence linking the alleged damages to any act or omission by Defendants. | I90: 20 | J90: UNREVIEWED | K90: Imported from JSON | L90: Medium | N90: YES
A91: E00090 | B91: REPLY-A11 | C91: I-SECDEP | D91: RELATES_TO | E91: MOTION_ASSERTION | H91: This failure is compounded by Plaintiff's lack of required notice, which independently bars recovery under Florida law. | I91: 18 | J91: UNREVIEWED | K91: Imported from JSON | L91: Medium | N91: YES
A92: E00091 | B92: REPLY-A12 | C92: DIN-169 | D92: PRECEDES | E92: MOTION_ASSERTION | I92: 25 | J92: UNREVIEWED | K92: Imported from JSON | L92: Medium | M92: Having failed to provide competent evidence and having destroyed key evidence, Plaintiff cannot avoid summary judgment. As a matter of law, it must be granted. | N92: NO
A93: E00092 | B93: Police_Report_2019-00042552 | C93: I-SPOLIATION | D93: SUPPORTS | E93: MOTION_ASSERTION | H93: Police Report #2019-00042552 documents Plaintiff's unauthorized removal and disposal of Defendant's property. | I93: 15 | J93: UNREVIEWED | K93: Imported from JSON | L93: Medium | N93: YES
A94: E00093 | B94: Def_Motion_Ex_11_Miami_Mold | C94: I-DAMAGES | D94: UNDERMINES_OPPOSING | E94: MOTION_ASSERTION | H94: Miami Mold's subpoenaed contemporaneous records (Def. Motion Ex. 11), which confirms 'no proof of payment exists.' | I94: 17 | J94: UNREVIEWED | K94: Imported from JSON | L94: Medium | N94: YES
A95: E00094 | B95: Manufacturer_Warranty | C95: E-WASH-01 | D95: RELATES_TO | E95: MOTION_ASSERTION | H95: The washer/dryer was under manufacturer warranty—it could have been repaired rather than destroyed. | I95: 15 | J95: UNREVIEWED | K95: Imported from JSON | L95: Medium | N95: YES
A96: E00095 | B96: Fla_R_Civ_P_1510 | C96: REPLY-A1 | D96: CITED_IN | E96: MOTION_ASSERTION | H96: The revised federal-aligned standard requires specific, admissible evidence demonstrating a genuine dispute of material fact. | I96: 16 | J96: UNREVIEWED | K96: Imported from JSON | L96: Medium | N96: YES
A97: E00096 | B97: Fla_R_Jud_Admin_2330h | C97: REPLY-A4 | D97: CITED_IN | E97: MOTION_ASSERTION | H97: Fla. R. Jud. Admin. 2.330(h) requires reconsideration of all rulings by a recused judge. | I97: 16 | J97: UNREVIEWED | K97: Imported from JSON | L97: Medium | N97: YES
A98: E00097 | B98: Public_Health_Trust_v_Valcin_507_So_2d_596_Fla_1987 | C98: REPLY-A7 | D98: CITED_IN | E98: MOTION_ASSERTION | H98: Under Public Health Trust v. Valcin, 507 So. 2d 596 (Fla. 1987), this mandates an adverse inference. | I98: 17 | J98: UNREVIEWED | K98: Imported from JSON | L98: Medium | N98: YES
A99: E00098 | B99: REPLY-A5 | C99: I-SPOLIATION | D99: SUPPORTS_ISSUE | E99: MOTION_ASSERTION | I99: 7 | J99: UNREVIEWED | K99: Imported from JSON | L99: Medium | M99: Assertion anchored to Police Report #2019-00042552 | N99: NO
A100: E00099 | B100: REPLY-A8 | C100: I-DAMAGES | D100: SUPPORTS_ISSUE | E100: MOTION_ASSERTION | I100: 7 | J100: UNREVIEWED | K100: Imported from JSON | L100: Medium | M100: Assertion anchored to Miami Mold Ex. 11 | N100: NO
A101: E00100 | B101: REPLY-A11 | C101: I-SECDEP | D101: RELATES_TO_ISSUE | E101: MOTION_ASSERTION | I101: 6 | J101: UNREVIEWED | K101: Imported from JSON | L101: Medium | M101: Assertion re: lack of required notice | N101: NO
A102: E00101 | B102: DIN-148 | C102: 2020-000746-CA-01 | D102: FILED_IN | E102: MOTION_ASSERTION | I102: 3 | J102: UNREVIEWED | K102: Imported from JSON | L102: Medium | M102: Record_Pages: 1036-1039 | N102: NO
A103: E00102 | B103: FOF-1 | C103: E-LEASE-01 | D103: ESTABLISHES | E103: COURT_FINDING | I103: 32 | J103: UNREVIEWED | K103: Imported from JSON | L103: Medium | M103: Plaintiff, Eli Cohen ('Plaintiff'), and Defendants, Jeff Atlas and Susan Atlas ('Defendants'), entered into a written residential lease agreement (the 'Lease') commencing on December 22, 2017 and ending on December 21, 2018 | N103: NO
A104: E00103 | B104: FOF-2 | C104: E-LEASE-01 | D104: ESTABLISHES | E104: COURT_FINDING | I104: 44 | J104: UNREVIEWED | K104: Imported from JSON | L104: Medium | M104: Section IX of the Lease allocates various maintenance responsibilities between Plaintiff as tenant and Defendants as landlords, and states that Plaintiff shall solely be responsible for maintaining three categories of items: (1) locks and keys; (2) furniture; and (3) heating and air conditioning filters. | N104: NO
...

Sheet ALIASES
A1: Alias_Entity_ID | B1: Canonical_Entity_ID | C1: Alias_Name | D1: Canonical_Name | E1: Reason | F1: Notes
A2: CIR-169/DIN169 | B2: DIN-169 | C2: CIR-169 / DIN 169 | D2: CIR-169 / DIN 169 | E2: Normalized docket identifier (DIN/CIR)
A3: CIR-99/DIN99 | B3: DIN-99 | C3: CIR-99 / DIN 99 | D3: CIR-99 / DIN 99 | E3: Normalized docket identifier (DIN/CIR)
A4: CIR-109/DIN109 | B4: DIN-109 | C4: CIR-109 / DIN 109 | D4: CIR-109 / DIN 109 | E4: Normalized docket identifier (DIN/CIR)
A5: CIR-135/DIN135 | B5: DIN-135 | C5: CIR-135 / DIN 135 | D5: CIR-135 / DIN 135 | E5: Normalized docket identifier (DIN/CIR)
A6: CIR-161/DIN161 | B6: DIN-161 | C6: CIR-161 / DIN 161 | D6: CIR-161 / DIN 161 | E6: Normalized docket identifier (DIN/CIR)
A7: CIR-164/DIN164 | B7: DIN-164 | C7: CIR-164 / DIN 164 | D7: CIR-164 / DIN 164 | E7: Normalized docket identifier (DIN/CIR)
A8: CIR-148/DIN148 | B8: DIN-148 | C8: CIR-148 / DIN 148 | D8: CIR-148 / DIN 148 | E8: Normalized docket identifier (DIN/CIR)
A9: CIR-151/DIN151 | B9: DIN-151 | C9: CIR-151 / DIN 151 | D9: CIR-151 / DIN 151 | E9: Normalized docket identifier (DIN/CIR)
A10: CIR-158/DIN158 | B10: DIN-158 | C10: CIR-158 / DIN 158 | D10: CIR-158 / DIN 158 | E10: Normalized docket identifier (DIN/CIR)
A11: CIR-170/DIN170 | B11: DIN-170 | C11: CIR-170 / DIN 170 | D11: CIR-170 / DIN 170 | E11: Normalized docket identifier (DIN/CIR)
A12: CIR-176/DIN176 | B12: DIN-176 | C12: CIR-176 / DIN 176 | D12: CIR-176 / DIN 176 | E12: Normalized docket identifier (DIN/CIR)
A13: CIR-178/DIN178 | B13: DIN-178 | C13: CIR-178 / DIN 178 | D13: CIR-178 / DIN 178 | E13: Normalized docket identifier (DIN/CIR)
A14: CIR-173/DIN173 | B14: DIN-173 | C14: CIR-173 / DIN 173 | D14: CIR-173 / DIN 173 | E14: Normalized docket identifier (DIN/CIR)
